[{"CFSAUID":"B1E","PRUID":"12","PRNAME":"Nova Scotia / Nouvelle-Écosse"},{"CFSAUID":"B1G","PRUID":"12","PRNAME":"Nova Scotia / Nouvelle-Écosse"},{"CFSAUID":"B1H","PRUID":"12","PRNAME":"Nova Scotia / Nouvelle-Écosse"},{"CFSAUID":"B1J","PRUID":"12","PRNAME":"Nova Scotia / Nouvelle-Écosse"},{"CFSAUID":"B1K","PRUID":"12","PRNAME":"Nova Scotia / Nouvelle-Écosse"},{"CFSAUID":"B1L","PRUID":"12","PRNAME":"Nova Scotia / Nouvelle-Écosse"},{"CFSAUID":"B1M","PRUID":"12","PRNAME":"Nova Scotia / Nouvelle-Écosse"},{"CFSAUID":"B1N","PRUID":"12","PRNAME":"Nova Scotia / Nouvelle-Écosse"},{"CFSAUID":"B1P","PRUID":"12","PRNAME":"Nova Scotia / Nouvelle-Écosse"},{"CFSAUID":"B1R","PRUID":"12","PRNAME":"Nova Scotia / Nouvelle-Écosse"},{"CFSAUID":"B1S","PRUID":"12","PRNAME":"Nova Scotia / Nouvelle-Écosse"},{"CFSAUID":"B1T","PRUID":"12","PRNAME":"Nova Scotia / Nouvelle-Écosse"},{"CFSAUID":"B1V","PRUID":"12","PRNAME":"Nova Scotia / Nouvelle-Écosse"},{"CFSAUID":"A1G","PRUID":"10","PRNAME":"Newfoundland and Labrador / Terre-Neuve-et-Labrador"},{"CFSAUID":"A1H","PRUID":"10","PRNAME":"Newfoundland and Labrador / Terre-Neuve-et-Labrador"},{"CFSAUID":"A1K","PRUID":"10","PRNAME":"Newfoundland and Labrador / Terre-Neuve-et-Labrador"},{"CFSAUID":"A1L","PRUID":"10","PRNAME":"Newfoundland and Labrador / Terre-Neuve-et-Labrador"},{"CFSAUID":"A1M","PRUID":"10","PRNAME":"Newfoundland and Labrador / Terre-Neuve-et-Labrador"},{"CFSAUID":"A1N","PRUID":"10","PRNAME":"Newfoundland and Labrador / Terre-Neuve-et-Labrador"},{"CFSAUID":"A1S","PRUID":"10","PRNAME":"Newfoundland and Labrador / Terre-Neuve-et-Labrador"},{"CFSAUID":"A0A","PRUID":"10","PRNAME":"Newfoundland and Labrador / Terre-Neuve-et-Labrador"},{"CFSAUID":"A0B","PRUID":"10","PRNAME":"Newfoundland and Labrador / Terre-Neuve-et-Labrador"},{"CFSAUID":"A0C","PRUID":"10","PRNAME":"Newfoundland and Labrador / Terre-Neuve-et-Labrador"},{"CFSAUID":"A0E","PRUID":"10","PRNAME":"Newfoundland and Labrador / Terre-Neuve-et-Labrador"},{"CFSAUID":"A0G","PRUID":"10","PRNAME":"Newfoundland and Labrador / Terre-Neuve-et-Labrador"},{"CFSAUID":"A0H","PRUID":"10","PRNAME":"Newfoundland and Labrador / Terre-Neuve-et-Labrador"},{"CFSAUID":"A0J","PRUID":"10","PRNAME":"Newfoundland and Labrador / Terre-Neuve-et-Labrador"},{"CFSAUID":"A0K","PRUID":"10","PRNAME":"Newfoundland and Labrador / Terre-Neuve-et-Labrador"},{"CFSAUID":"A0L","PRUID":"10","PRNAME":"Newfoundland and Labrador / Terre-Neuve-et-Labrador"},{"CFSAUID":"A0M","PRUID":"10","PRNAME":"Newfoundland and Labrador / Terre-Neuve-et-Labrador"},{"CFSAUID":"A0N","PRUID":"10","PRNAME":"Newfoundland and Labrador / Terre-Neuve-et-Labrador"},{"CFSAUID":"A0P","PRUID":"10","PRNAME":"Newfoundland and Labrador / Terre-Neuve-et-Labrador"},{"CFSAUID":"A0R","PRUID":"10","PRNAME":"Newfoundland and Labrador / Terre-Neuve-et-Labrador"},{"CFSAUID":"A1A","PRUID":"10","PRNAME":"Newfoundland and Labrador / Terre-Neuve-et-Labrador"},{"CFSAUID":"A1B","PRUID":"10","PRNAME":"Newfoundland and Labrador / Terre-Neuve-et-Labrador"},{"CFSAUID":"A1C","PRUID":"10","PRNAME":"Newfoundland and Labrador / Terre-Neuve-et-Labrador"},{"CFSAUID":"A1E","PRUID":"10","PRNAME":"Newfoundland and Labrador / Terre-Neuve-et-Labrador"},{"CFSAUID":"A1V","PRUID":"10","PRNAME":"Newfoundland and Labrador / Terre-Neuve-et-Labrador"},{"CFSAUID":"A1W","PRUID":"10","PRNAME":"Newfoundland and Labrador / Terre-Neuve-et-Labrador"},{"CFSAUID":"A1X","PRUID":"10","PRNAME":"Newfoundland and Labrador / Terre-Neuve-et-Labrador"},{"CFSAUID":"A1Y","PRUID":"10","PRNAME":"Newfoundland and Labrador / Terre-Neuve-et-Labrador"},{"CFSAUID":"A2A","PRUID":"10","PRNAME":"Newfoundland and Labrador / Terre-Neuve-et-Labrador"},{"CFSAUID":"A2B","PRUID":"10","PRNAME":"Newfoundland and Labrador / Terre-Neuve-et-Labrador"},{"CFSAUID":"A2H","PRUID":"10","PRNAME":"Newfoundland and Labrador / Terre-Neuve-et-Labrador"},{"CFSAUID":"A2N","PRUID":"10","PRNAME":"Newfoundland and Labrador / Terre-Neuve-et-Labrador"},{"CFSAUID":"A2V","PRUID":"10","PRNAME":"Newfoundland and Labrador / Terre-Neuve-et-Labrador"},{"CFSAUID":"A5A","PRUID":"10","PRNAME":"Newfoundland and Labrador / Terre-Neuve-et-Labrador"},{"CFSAUID":"A8A","PRUID":"10","PRNAME":"Newfoundland and Labrador / Terre-Neuve-et-Labrador"},{"CFSAUID":"B0C","PRUID":"12","PRNAME":"Nova Scotia / Nouvelle-Écosse"},{"CFSAUID":"B0E","PRUID":"12","PRNAME":"Nova Scotia / Nouvelle-Écosse"},{"CFSAUID":"B0H","PRUID":"12","PRNAME":"Nova Scotia / Nouvelle-Écosse"},{"CFSAUID":"B0J","PRUID":"12","PRNAME":"Nova Scotia / Nouvelle-Écosse"},{"CFSAUID":"B0K","PRUID":"12","PRNAME":"Nova Scotia / Nouvelle-Écosse"},{"CFSAUID":"B0L","PRUID":"12","PRNAME":"Nova Scotia / Nouvelle-Écosse"},{"CFSAUID":"B0M","PRUID":"12","PRNAME":"Nova Scotia / Nouvelle-Écosse"},{"CFSAUID":"B0N","PRUID":"12","PRNAME":"Nova Scotia / Nouvelle-Écosse"},{"CFSAUID":"B0P","PRUID":"12","PRNAME":"Nova Scotia / Nouvelle-Écosse"},{"CFSAUID":"B0R","PRUID":"12","PRNAME":"Nova Scotia / Nouvelle-Écosse"},{"CFSAUID":"B0S","PRUID":"12","PRNAME":"Nova Scotia / Nouvelle-Écosse"},{"CFSAUID":"B0T","PRUID":"12","PRNAME":"Nova Scotia / Nouvelle-Écosse"},{"CFSAUID":"B0V","PRUID":"12","PRNAME":"Nova Scotia / Nouvelle-Écosse"},{"CFSAUID":"B0W","PRUID":"12","PRNAME":"Nova Scotia / Nouvelle-Écosse"},{"CFSAUID":"B1A","PRUID":"12","PRNAME":"Nova Scotia / Nouvelle-Écosse"},{"CFSAUID":"B1B","PRUID":"12","PRNAME":"Nova Scotia / Nouvelle-Écosse"},{"CFSAUID":"B1C","PRUID":"12","PRNAME":"Nova Scotia / Nouvelle-Écosse"},{"CFSAUID":"B3B","PRUID":"12","PRNAME":"Nova Scotia / Nouvelle-Écosse"},{"CFSAUID":"B3H","PRUID":"12","PRNAME":"Nova Scotia / Nouvelle-Écosse"},{"CFSAUID":"B3J","PRUID":"12","PRNAME":"Nova Scotia / Nouvelle-Écosse"},{"CFSAUID":"B3K","PRUID":"12","PRNAME":"Nova Scotia / Nouvelle-Écosse"},{"CFSAUID":"B3L","PRUID":"12","PRNAME":"Nova Scotia / Nouvelle-Écosse"},{"CFSAUID":"B3M","PRUID":"12","PRNAME":"Nova Scotia / Nouvelle-Écosse"},{"CFSAUID":"B3R","PRUID":"12","PRNAME":"Nova Scotia / Nouvelle-Écosse"},{"CFSAUID":"B3S","PRUID":"12","PRNAME":"Nova Scotia / Nouvelle-Écosse"},{"CFSAUID":"B3T","PRUID":"12","PRNAME":"Nova Scotia / Nouvelle-Écosse"},{"CFSAUID":"B3V","PRUID":"12","PRNAME":"Nova Scotia / Nouvelle-Écosse"},{"CFSAUID":"B3Z","PRUID":"12","PRNAME":"Nova Scotia / Nouvelle-Écosse"},{"CFSAUID":"B4A","PRUID":"12","PRNAME":"Nova Scotia / Nouvelle-Écosse"},{"CFSAUID":"B4B","PRUID":"12","PRNAME":"Nova Scotia / Nouvelle-Écosse"},{"CFSAUID":"B4C","PRUID":"12","PRNAME":"Nova Scotia / Nouvelle-Écosse"},{"CFSAUID":"B4E","PRUID":"12","PRNAME":"Nova Scotia / Nouvelle-Écosse"},{"CFSAUID":"B4H","PRUID":"12","PRNAME":"Nova Scotia / Nouvelle-Écosse"},{"CFSAUID":"B4N","PRUID":"12","PRNAME":"Nova Scotia / Nouvelle-Écosse"},{"CFSAUID":"B4G","PRUID":"12","PRNAME":"Nova Scotia / Nouvelle-Écosse"},{"CFSAUID":"B4P","PRUID":"12","PRNAME":"Nova Scotia / Nouvelle-Écosse"},{"CFSAUID":"B4R","PRUID":"12","PRNAME":"Nova Scotia / Nouvelle-Écosse"},{"CFSAUID":"B4V","PRUID":"12","PRNAME":"Nova Scotia / Nouvelle-Écosse"},{"CFSAUID":"B5A","PRUID":"12","PRNAME":"Nova Scotia / Nouvelle-Écosse"},{"CFSAUID":"B6L","PRUID":"12","PRNAME":"Nova Scotia / Nouvelle-Écosse"},{"CFSAUID":"B9A","PRUID":"12","PRNAME":"Nova Scotia / Nouvelle-Écosse"},{"CFSAUID":"C0A","PRUID":"11","PRNAME":"Prince Edward Island / Île-du-Prince-Édouard"},{"CFSAUID":"C0B","PRUID":"11","PRNAME":"Prince Edward Island / Île-du-Prince-Édouard"},{"CFSAUID":"C1B","PRUID":"11","PRNAME":"Prince Edward Island / Île-du-Prince-Édouard"},{"CFSAUID":"C1A","PRUID":"11","PRNAME":"Prince Edward Island / Île-du-Prince-Édouard"},{"CFSAUID":"C1C","PRUID":"11","PRNAME":"Prince Edward Island / Île-du-Prince-Édouard"},{"CFSAUID":"C1E","PRUID":"11","PRNAME":"Prince Edward Island / Île-du-Prince-Édouard"},{"CFSAUID":"C1N","PRUID":"11","PRNAME":"Prince Edward Island / Île-du-Prince-Édouard"},{"CFSAUID":"E1A","PRUID":"13","PRNAME":"New Brunswick / Nouveau-Brunswick"},{"CFSAUID":"E1B","PRUID":"13","PRNAME":"New Brunswick / Nouveau-Brunswick"},{"CFSAUID":"E1C","PRUID":"13","PRNAME":"New Brunswick / Nouveau-Brunswick"},{"CFSAUID":"B1W","PRUID":"12","PRNAME":"Nova Scotia / Nouvelle-Écosse"},{"CFSAUID":"B1X","PRUID":"12","PRNAME":"Nova Scotia / Nouvelle-Écosse"},{"CFSAUID":"B1Y","PRUID":"12","PRNAME":"Nova Scotia / Nouvelle-Écosse"},{"CFSAUID":"B2A","PRUID":"12","PRNAME":"Nova Scotia / Nouvelle-Écosse"},{"CFSAUID":"B2C","PRUID":"12","PRNAME":"Nova Scotia / Nouvelle-Écosse"},{"CFSAUID":"B2E","PRUID":"12","PRNAME":"Nova Scotia / Nouvelle-Écosse"},{"CFSAUID":"B2G","PRUID":"12","PRNAME":"Nova Scotia / Nouvelle-Écosse"},{"CFSAUID":"B2H","PRUID":"12","PRNAME":"Nova Scotia / Nouvelle-Écosse"},{"CFSAUID":"B2J","PRUID":"12","PRNAME":"Nova Scotia / Nouvelle-Écosse"},{"CFSAUID":"B2N","PRUID":"12","PRNAME":"Nova Scotia / Nouvelle-Écosse"},{"CFSAUID":"B2R","PRUID":"12","PRNAME":"Nova Scotia / Nouvelle-Écosse"},{"CFSAUID":"B2S","PRUID":"12","PRNAME":"Nova Scotia / Nouvelle-Écosse"},{"CFSAUID":"B2T","PRUID":"12","PRNAME":"Nova Scotia / Nouvelle-Écosse"},{"CFSAUID":"B2V","PRUID":"12","PRNAME":"Nova Scotia / Nouvelle-Écosse"},{"CFSAUID":"B2W","PRUID":"12","PRNAME":"Nova Scotia / Nouvelle-Écosse"},{"CFSAUID":"B2Z","PRUID":"12","PRNAME":"Nova Scotia / Nouvelle-Écosse"},{"CFSAUID":"B3A","PRUID":"12","PRNAME":"Nova Scotia / Nouvelle-Écosse"},{"CFSAUID":"B3E","PRUID":"12","PRNAME":"Nova Scotia / Nouvelle-Écosse"},{"CFSAUID":"B3G","PRUID":"12","PRNAME":"Nova Scotia / Nouvelle-Écosse"},{"CFSAUID":"B3N","PRUID":"12","PRNAME":"Nova Scotia / Nouvelle-Écosse"},{"CFSAUID":"B3P","PRUID":"12","PRNAME":"Nova Scotia / Nouvelle-Écosse"},{"CFSAUID":"B2X","PRUID":"12","PRNAME":"Nova Scotia / Nouvelle-Écosse"},{"CFSAUID":"B2Y","PRUID":"12","PRNAME":"Nova Scotia / Nouvelle-Écosse"},{"CFSAUID":"E1E","PRUID":"13","PRNAME":"New Brunswick / Nouveau-Brunswick"},{"CFSAUID":"E1J","PRUID":"13","PRNAME":"New Brunswick / Nouveau-Brunswick"},{"CFSAUID":"E1N","PRUID":"13","PRNAME":"New Brunswick / Nouveau-Brunswick"},{"CFSAUID":"E1V","PRUID":"13","PRNAME":"New Brunswick / Nouveau-Brunswick"},{"CFSAUID":"E1W","PRUID":"13","PRNAME":"New Brunswick / Nouveau-Brunswick"},{"CFSAUID":"E1X","PRUID":"13","PRNAME":"New Brunswick / Nouveau-Brunswick"},{"CFSAUID":"E2A","PRUID":"13","PRNAME":"New Brunswick / Nouveau-Brunswick"},{"CFSAUID":"E2E","PRUID":"13","PRNAME":"New Brunswick / Nouveau-Brunswick"},{"CFSAUID":"E2G","PRUID":"13","PRNAME":"New Brunswick / Nouveau-Brunswick"},{"CFSAUID":"E2H","PRUID":"13","PRNAME":"New Brunswick / Nouveau-Brunswick"},{"CFSAUID":"E2J","PRUID":"13","PRNAME":"New Brunswick / Nouveau-Brunswick"},{"CFSAUID":"E2K","PRUID":"13","PRNAME":"New Brunswick / Nouveau-Brunswick"},{"CFSAUID":"E2L","PRUID":"13","PRNAME":"New Brunswick / Nouveau-Brunswick"},{"CFSAUID":"E2M","PRUID":"13","PRNAME":"New Brunswick / Nouveau-Brunswick"},{"CFSAUID":"E2N","PRUID":"13","PRNAME":"New Brunswick / Nouveau-Brunswick"},{"CFSAUID":"E2P","PRUID":"13","PRNAME":"New Brunswick / Nouveau-Brunswick"},{"CFSAUID":"E2S","PRUID":"13","PRNAME":"New Brunswick / Nouveau-Brunswick"},{"CFSAUID":"E3A","PRUID":"13","PRNAME":"New Brunswick / Nouveau-Brunswick"},{"CFSAUID":"E3B","PRUID":"13","PRNAME":"New Brunswick / Nouveau-Brunswick"},{"CFSAUID":"E3C","PRUID":"13","PRNAME":"New Brunswick / Nouveau-Brunswick"},{"CFSAUID":"E3E","PRUID":"13","PRNAME":"New Brunswick / Nouveau-Brunswick"},{"CFSAUID":"E3G","PRUID":"13","PRNAME":"New Brunswick / Nouveau-Brunswick"},{"CFSAUID":"E3L","PRUID":"13","PRNAME":"New Brunswick / Nouveau-Brunswick"},{"CFSAUID":"E3N","PRUID":"13","PRNAME":"New Brunswick / Nouveau-Brunswick"},{"CFSAUID":"E2V","PRUID":"13","PRNAME":"New Brunswick / Nouveau-Brunswick"},{"CFSAUID":"E3V","PRUID":"13","PRNAME":"New Brunswick / Nouveau-Brunswick"},{"CFSAUID":"E3Y","PRUID":"13","PRNAME":"New Brunswick / Nouveau-Brunswick"},{"CFSAUID":"E3Z","PRUID":"13","PRNAME":"New Brunswick / Nouveau-Brunswick"},{"CFSAUID":"E4A","PRUID":"13","PRNAME":"New Brunswick / Nouveau-Brunswick"},{"CFSAUID":"E4B","PRUID":"13","PRNAME":"New Brunswick / Nouveau-Brunswick"},{"CFSAUID":"E4W","PRUID":"13","PRNAME":"New Brunswick / Nouveau-Brunswick"},{"CFSAUID":"E4X","PRUID":"13","PRNAME":"New Brunswick / Nouveau-Brunswick"},{"CFSAUID":"E4Y","PRUID":"13","PRNAME":"New Brunswick / Nouveau-Brunswick"},{"CFSAUID":"E4Z","PRUID":"13","PRNAME":"New Brunswick / Nouveau-Brunswick"},{"CFSAUID":"E5A","PRUID":"13","PRNAME":"New Brunswick / Nouveau-Brunswick"},{"CFSAUID":"E5B","PRUID":"13","PRNAME":"New Brunswick / Nouveau-Brunswick"},{"CFSAUID":"E5C","PRUID":"13","PRNAME":"New Brunswick / Nouveau-Brunswick"},{"CFSAUID":"E5E","PRUID":"13","PRNAME":"New Brunswick / Nouveau-Brunswick"},{"CFSAUID":"E5G","PRUID":"13","PRNAME":"New Brunswick / Nouveau-Brunswick"},{"CFSAUID":"E5H","PRUID":"13","PRNAME":"New Brunswick / Nouveau-Brunswick"},{"CFSAUID":"E5J","PRUID":"13","PRNAME":"New Brunswick / Nouveau-Brunswick"},{"CFSAUID":"E5K","PRUID":"13","PRNAME":"New Brunswick / Nouveau-Brunswick"},{"CFSAUID":"E5L","PRUID":"13","PRNAME":"New Brunswick / Nouveau-Brunswick"},{"CFSAUID":"E5M","PRUID":"13","PRNAME":"New Brunswick / Nouveau-Brunswick"},{"CFSAUID":"E5N","PRUID":"13","PRNAME":"New Brunswick / Nouveau-Brunswick"},{"CFSAUID":"E5P","PRUID":"13","PRNAME":"New Brunswick / Nouveau-Brunswick"},{"CFSAUID":"E5R","PRUID":"13","PRNAME":"New Brunswick / Nouveau-Brunswick"},{"CFSAUID":"E5S","PRUID":"13","PRNAME":"New Brunswick / Nouveau-Brunswick"},{"CFSAUID":"E5T","PRUID":"13","PRNAME":"New Brunswick / Nouveau-Brunswick"},{"CFSAUID":"E5V","PRUID":"13","PRNAME":"New Brunswick / Nouveau-Brunswick"},{"CFSAUID":"E6A","PRUID":"13","PRNAME":"New Brunswick / Nouveau-Brunswick"},{"CFSAUID":"E6B","PRUID":"13","PRNAME":"New Brunswick / Nouveau-Brunswick"},{"CFSAUID":"E6C","PRUID":"13","PRNAME":"New Brunswick / Nouveau-Brunswick"},{"CFSAUID":"E6E","PRUID":"13","PRNAME":"New Brunswick / Nouveau-Brunswick"},{"CFSAUID":"E6G","PRUID":"13","PRNAME":"New Brunswick / Nouveau-Brunswick"},{"CFSAUID":"E6H","PRUID":"13","PRNAME":"New Brunswick / Nouveau-Brunswick"},{"CFSAUID":"E6J","PRUID":"13","PRNAME":"New Brunswick / Nouveau-Brunswick"},{"CFSAUID":"E6K","PRUID":"13","PRNAME":"New Brunswick / Nouveau-Brunswick"},{"CFSAUID":"E6L","PRUID":"13","PRNAME":"New Brunswick / Nouveau-Brunswick"},{"CFSAUID":"E7B","PRUID":"13","PRNAME":"New Brunswick / Nouveau-Brunswick"},{"CFSAUID":"E7C","PRUID":"13","PRNAME":"New Brunswick / Nouveau-Brunswick"},{"CFSAUID":"E7A","PRUID":"13","PRNAME":"New Brunswick / Nouveau-Brunswick"},{"CFSAUID":"E7E","PRUID":"13","PRNAME":"New Brunswick / Nouveau-Brunswick"},{"CFSAUID":"E7G","PRUID":"13","PRNAME":"New Brunswick / Nouveau-Brunswick"},{"CFSAUID":"E7H","PRUID":"13","PRNAME":"New Brunswick / Nouveau-Brunswick"},{"CFSAUID":"E7J","PRUID":"13","PRNAME":"New Brunswick / Nouveau-Brunswick"},{"CFSAUID":"E7K","PRUID":"13","PRNAME":"New Brunswick / Nouveau-Brunswick"},{"CFSAUID":"E7L","PRUID":"13","PRNAME":"New Brunswick / Nouveau-Brunswick"},{"CFSAUID":"E7M","PRUID":"13","PRNAME":"New Brunswick / Nouveau-Brunswick"},{"CFSAUID":"E7N","PRUID":"13","PRNAME":"New Brunswick / Nouveau-Brunswick"},{"CFSAUID":"E7P","PRUID":"13","PRNAME":"New Brunswick / Nouveau-Brunswick"},{"CFSAUID":"E8A","PRUID":"13","PRNAME":"New Brunswick / Nouveau-Brunswick"},{"CFSAUID":"E8B","PRUID":"13","PRNAME":"New Brunswick / Nouveau-Brunswick"},{"CFSAUID":"E4E","PRUID":"13","PRNAME":"New Brunswick / Nouveau-Brunswick"},{"CFSAUID":"E4G","PRUID":"13","PRNAME":"New Brunswick / Nouveau-Brunswick"},{"CFSAUID":"E4C","PRUID":"13","PRNAME":"New Brunswick / Nouveau-Brunswick"},{"CFSAUID":"E4H","PRUID":"13","PRNAME":"New Brunswick / Nouveau-Brunswick"},{"CFSAUID":"E4J","PRUID":"13","PRNAME":"New Brunswick / Nouveau-Brunswick"},{"CFSAUID":"E4K","PRUID":"13","PRNAME":"New Brunswick / Nouveau-Brunswick"},{"CFSAUID":"E4L","PRUID":"13","PRNAME":"New Brunswick / Nouveau-Brunswick"},{"CFSAUID":"E4M","PRUID":"13","PRNAME":"New Brunswick / Nouveau-Brunswick"},{"CFSAUID":"E4N","PRUID":"13","PRNAME":"New Brunswick / Nouveau-Brunswick"},{"CFSAUID":"E4P","PRUID":"13","PRNAME":"New Brunswick / Nouveau-Brunswick"},{"CFSAUID":"E4R","PRUID":"13","PRNAME":"New Brunswick / Nouveau-Brunswick"},{"CFSAUID":"E4S","PRUID":"13","PRNAME":"New Brunswick / Nouveau-Brunswick"},{"CFSAUID":"E4T","PRUID":"13","PRNAME":"New Brunswick / Nouveau-Brunswick"},{"CFSAUID":"E4V","PRUID":"13","PRNAME":"New Brunswick / Nouveau-Brunswick"},{"CFSAUID":"E1G","PRUID":"13","PRNAME":"New Brunswick / Nouveau-Brunswick"},{"CFSAUID":"E1H","PRUID":"13","PRNAME":"New Brunswick / Nouveau-Brunswick"},{"CFSAUID":"G1M","PRUID":"24","PRNAME":"Quebec / Québec"},{"CFSAUID":"G1N","PRUID":"24","PRNAME":"Quebec / Québec"},{"CFSAUID":"G1P","PRUID":"24","PRNAME":"Quebec / Québec"},{"CFSAUID":"G1R","PRUID":"24","PRNAME":"Quebec / Québec"},{"CFSAUID":"G1S","PRUID":"24","PRNAME":"Quebec / Québec"},{"CFSAUID":"G1T","PRUID":"24","PRNAME":"Quebec / Québec"},{"CFSAUID":"G1V","PRUID":"24","PRNAME":"Quebec / Québec"},{"CFSAUID":"G1W","PRUID":"24","PRNAME":"Quebec / Québec"},{"CFSAUID":"E8C","PRUID":"13","PRNAME":"New Brunswick / Nouveau-Brunswick"},{"CFSAUID":"E8E","PRUID":"13","PRNAME":"New Brunswick / Nouveau-Brunswick"},{"CFSAUID":"E8G","PRUID":"13","PRNAME":"New Brunswick / Nouveau-Brunswick"},{"CFSAUID":"E8J","PRUID":"13","PRNAME":"New Brunswick / Nouveau-Brunswick"},{"CFSAUID":"E8K","PRUID":"13","PRNAME":"New Brunswick / Nouveau-Brunswick"},{"CFSAUID":"E8L","PRUID":"13","PRNAME":"New Brunswick / Nouveau-Brunswick"},{"CFSAUID":"E8M","PRUID":"13","PRNAME":"New Brunswick / Nouveau-Brunswick"},{"CFSAUID":"E8N","PRUID":"13","PRNAME":"New Brunswick / Nouveau-Brunswick"},{"CFSAUID":"E8P","PRUID":"13","PRNAME":"New Brunswick / Nouveau-Brunswick"},{"CFSAUID":"E8R","PRUID":"13","PRNAME":"New Brunswick / Nouveau-Brunswick"},{"CFSAUID":"E8S","PRUID":"13","PRNAME":"New Brunswick / Nouveau-Brunswick"},{"CFSAUID":"E8T","PRUID":"13","PRNAME":"New Brunswick / Nouveau-Brunswick"},{"CFSAUID":"E9A","PRUID":"13","PRNAME":"New Brunswick / Nouveau-Brunswick"},{"CFSAUID":"E9B","PRUID":"13","PRNAME":"New Brunswick / Nouveau-Brunswick"},{"CFSAUID":"E9C","PRUID":"13","PRNAME":"New Brunswick / Nouveau-Brunswick"},{"CFSAUID":"E9E","PRUID":"13","PRNAME":"New Brunswick / Nouveau-Brunswick"},{"CFSAUID":"E9G","PRUID":"13","PRNAME":"New Brunswick / Nouveau-Brunswick"},{"CFSAUID":"E9H","PRUID":"13","PRNAME":"New Brunswick / Nouveau-Brunswick"},{"CFSAUID":"G0A","PRUID":"24","PRNAME":"Quebec / Québec"},{"CFSAUID":"G0C","PRUID":"24","PRNAME":"Quebec / Québec"},{"CFSAUID":"G0E","PRUID":"24","PRNAME":"Quebec / Québec"},{"CFSAUID":"G0G","PRUID":"24","PRNAME":"Quebec / Québec"},{"CFSAUID":"G0H","PRUID":"24","PRNAME":"Quebec / Québec"},{"CFSAUID":"G0J","PRUID":"24","PRNAME":"Quebec / Québec"},{"CFSAUID":"G0K","PRUID":"24","PRNAME":"Quebec / Québec"},{"CFSAUID":"G0L","PRUID":"24","PRNAME":"Quebec / Québec"},{"CFSAUID":"G0M","PRUID":"24","PRNAME":"Quebec / Québec"},{"CFSAUID":"G0N","PRUID":"24","PRNAME":"Quebec / Québec"},{"CFSAUID":"G0P","PRUID":"24","PRNAME":"Quebec / Québec"},{"CFSAUID":"G0R","PRUID":"24","PRNAME":"Quebec / Québec"},{"CFSAUID":"G0S","PRUID":"24","PRNAME":"Quebec / Québec"},{"CFSAUID":"G0T","PRUID":"24","PRNAME":"Quebec / Québec"},{"CFSAUID":"G0V","PRUID":"24","PRNAME":"Quebec / Québec"},{"CFSAUID":"G0W","PRUID":"24","PRNAME":"Quebec / Québec"},{"CFSAUID":"G0X","PRUID":"24","PRNAME":"Quebec / Québec"},{"CFSAUID":"G0Y","PRUID":"24","PRNAME":"Quebec / Québec"},{"CFSAUID":"G0Z","PRUID":"24","PRNAME":"Quebec / Québec"},{"CFSAUID":"G1B","PRUID":"24","PRNAME":"Quebec / Québec"},{"CFSAUID":"G1C","PRUID":"24","PRNAME":"Quebec / Québec"},{"CFSAUID":"G1E","PRUID":"24","PRNAME":"Quebec / Québec"},{"CFSAUID":"G1G","PRUID":"24","PRNAME":"Quebec / Québec"},{"CFSAUID":"G1H","PRUID":"24","PRNAME":"Quebec / Québec"},{"CFSAUID":"G1J","PRUID":"24","PRNAME":"Quebec / Québec"},{"CFSAUID":"G1K","PRUID":"24","PRNAME":"Quebec / Québec"},{"CFSAUID":"G1L","PRUID":"24","PRNAME":"Quebec / Québec"},{"CFSAUID":"G1X","PRUID":"24","PRNAME":"Quebec / Québec"},{"CFSAUID":"G1Y","PRUID":"24","PRNAME":"Quebec / Québec"},{"CFSAUID":"G2A","PRUID":"24","PRNAME":"Quebec / Québec"},{"CFSAUID":"G2B","PRUID":"24","PRNAME":"Quebec / Québec"},{"CFSAUID":"G2C","PRUID":"24","PRNAME":"Quebec / Québec"},{"CFSAUID":"G2E","PRUID":"24","PRNAME":"Quebec / Québec"},{"CFSAUID":"G2G","PRUID":"24","PRNAME":"Quebec / Québec"},{"CFSAUID":"G2J","PRUID":"24","PRNAME":"Quebec / Québec"},{"CFSAUID":"G2K","PRUID":"24","PRNAME":"Quebec / Québec"},{"CFSAUID":"G3B","PRUID":"24","PRNAME":"Quebec / Québec"},{"CFSAUID":"G3C","PRUID":"24","PRNAME":"Quebec / Québec"},{"CFSAUID":"G3E","PRUID":"24","PRNAME":"Quebec / Québec"},{"CFSAUID":"G3G","PRUID":"24","PRNAME":"Quebec / Québec"},{"CFSAUID":"G3H","PRUID":"24","PRNAME":"Quebec / Québec"},{"CFSAUID":"G3J","PRUID":"24","PRNAME":"Quebec / Québec"},{"CFSAUID":"G3K","PRUID":"24","PRNAME":"Quebec / Québec"},{"CFSAUID":"G3L","PRUID":"24","PRNAME":"Quebec / Québec"},{"CFSAUID":"G3Z","PRUID":"24","PRNAME":"Quebec / Québec"},{"CFSAUID":"G4R","PRUID":"24","PRNAME":"Quebec / Québec"},{"CFSAUID":"G4S","PRUID":"24","PRNAME":"Quebec / Québec"},{"CFSAUID":"G4T","PRUID":"24","PRNAME":"Quebec / Québec"},{"CFSAUID":"G3M","PRUID":"24","PRNAME":"Quebec / Québec"},{"CFSAUID":"G3N","PRUID":"24","PRNAME":"Quebec / Québec"},{"CFSAUID":"G4A","PRUID":"24","PRNAME":"Quebec / Québec"},{"CFSAUID":"G4V","PRUID":"24","PRNAME":"Quebec / Québec"},{"CFSAUID":"G4W","PRUID":"24","PRNAME":"Quebec / Québec"},{"CFSAUID":"G4X","PRUID":"24","PRNAME":"Quebec / Québec"},{"CFSAUID":"G4Z","PRUID":"24","PRNAME":"Quebec / Québec"},{"CFSAUID":"G5A","PRUID":"24","PRNAME":"Quebec / Québec"},{"CFSAUID":"G5B","PRUID":"24","PRNAME":"Quebec / Québec"},{"CFSAUID":"G5C","PRUID":"24","PRNAME":"Quebec / Québec"},{"CFSAUID":"G2L","PRUID":"24","PRNAME":"Quebec / Québec"},{"CFSAUID":"G2M","PRUID":"24","PRNAME":"Quebec / Québec"},{"CFSAUID":"G2N","PRUID":"24","PRNAME":"Quebec / Québec"},{"CFSAUID":"G3A","PRUID":"24","PRNAME":"Quebec / Québec"},{"CFSAUID":"G6C","PRUID":"24","PRNAME":"Quebec / Québec"},{"CFSAUID":"G6J","PRUID":"24","PRNAME":"Quebec / Québec"},{"CFSAUID":"G6K","PRUID":"24","PRNAME":"Quebec / Québec"},{"CFSAUID":"G6L","PRUID":"24","PRNAME":"Quebec / Québec"},{"CFSAUID":"G6P","PRUID":"24","PRNAME":"Quebec / Québec"},{"CFSAUID":"G6R","PRUID":"24","PRNAME":"Quebec / Québec"},{"CFSAUID":"G6S","PRUID":"24","PRNAME":"Quebec / Québec"},{"CFSAUID":"G6T","PRUID":"24","PRNAME":"Quebec / Québec"},{"CFSAUID":"G6V","PRUID":"24","PRNAME":"Quebec / Québec"},{"CFSAUID":"G6W","PRUID":"24","PRNAME":"Quebec / Québec"},{"CFSAUID":"G6X","PRUID":"24","PRNAME":"Quebec / Québec"},{"CFSAUID":"G6Y","PRUID":"24","PRNAME":"Quebec / Québec"},{"CFSAUID":"G7A","PRUID":"24","PRNAME":"Quebec / Québec"},{"CFSAUID":"G7H","PRUID":"24","PRNAME":"Quebec / Québec"},{"CFSAUID":"G7P","PRUID":"24","PRNAME":"Quebec / Québec"},{"CFSAUID":"G7S","PRUID":"24","PRNAME":"Quebec / Québec"},{"CFSAUID":"G9A","PRUID":"24","PRNAME":"Quebec / Québec"},{"CFSAUID":"G9B","PRUID":"24","PRNAME":"Quebec / Québec"},{"CFSAUID":"G9H","PRUID":"24","PRNAME":"Quebec / Québec"},{"CFSAUID":"G9N","PRUID":"24","PRNAME":"Quebec / Québec"},{"CFSAUID":"G9T","PRUID":"24","PRNAME":"Quebec / Québec"},{"CFSAUID":"G9X","PRUID":"24","PRNAME":"Quebec / Québec"},{"CFSAUID":"H0M","PRUID":"24","PRNAME":"Quebec / Québec"},{"CFSAUID":"H1A","PRUID":"24","PRNAME":"Quebec / Québec"},{"CFSAUID":"G6Z","PRUID":"24","PRNAME":"Quebec / Québec"},{"CFSAUID":"G7B","PRUID":"24","PRNAME":"Quebec / Québec"},{"CFSAUID":"G7G","PRUID":"24","PRNAME":"Quebec / Québec"},{"CFSAUID":"G7J","PRUID":"24","PRNAME":"Quebec / Québec"},{"CFSAUID":"G7K","PRUID":"24","PRNAME":"Quebec / Québec"},{"CFSAUID":"G7N","PRUID":"24","PRNAME":"Quebec / Québec"},{"CFSAUID":"G7T","PRUID":"24","PRNAME":"Quebec / Québec"},{"CFSAUID":"G7X","PRUID":"24","PRNAME":"Quebec / Québec"},{"CFSAUID":"G7Y","PRUID":"24","PRNAME":"Quebec / Québec"},{"CFSAUID":"G7Z","PRUID":"24","PRNAME":"Quebec / Québec"},{"CFSAUID":"G8A","PRUID":"24","PRNAME":"Quebec / Québec"},{"CFSAUID":"G8B","PRUID":"24","PRNAME":"Quebec / Québec"},{"CFSAUID":"G8C","PRUID":"24","PRNAME":"Quebec / Québec"},{"CFSAUID":"G8E","PRUID":"24","PRNAME":"Quebec / Québec"},{"CFSAUID":"G8G","PRUID":"24","PRNAME":"Quebec / Québec"},{"CFSAUID":"G8H","PRUID":"24","PRNAME":"Quebec / Québec"},{"CFSAUID":"G8J","PRUID":"24","PRNAME":"Quebec / Québec"},{"CFSAUID":"G8K","PRUID":"24","PRNAME":"Quebec / Québec"},{"CFSAUID":"G8L","PRUID":"24","PRNAME":"Quebec / Québec"},{"CFSAUID":"G8M","PRUID":"24","PRNAME":"Quebec / Québec"},{"CFSAUID":"G8N","PRUID":"24","PRNAME":"Quebec / Québec"},{"CFSAUID":"G8P","PRUID":"24","PRNAME":"Quebec / Québec"},{"CFSAUID":"G8T","PRUID":"24","PRNAME":"Quebec / Québec"},{"CFSAUID":"G8V","PRUID":"24","PRNAME":"Quebec / Québec"},{"CFSAUID":"G5H","PRUID":"24","PRNAME":"Quebec / Québec"},{"CFSAUID":"G5J","PRUID":"24","PRNAME":"Quebec / Québec"},{"CFSAUID":"G5L","PRUID":"24","PRNAME":"Quebec / Québec"},{"CFSAUID":"G5M","PRUID":"24","PRNAME":"Quebec / Québec"},{"CFSAUID":"G5N","PRUID":"24","PRNAME":"Quebec / Québec"},{"CFSAUID":"G5Y","PRUID":"24","PRNAME":"Quebec / Québec"},{"CFSAUID":"G5Z","PRUID":"24","PRNAME":"Quebec / Québec"},{"CFSAUID":"G5R","PRUID":"24","PRNAME":"Quebec / Québec"},{"CFSAUID":"G5T","PRUID":"24","PRNAME":"Quebec / Québec"},{"CFSAUID":"G5V","PRUID":"24","PRNAME":"Quebec / Québec"},{"CFSAUID":"G5X","PRUID":"24","PRNAME":"Quebec / Québec"},{"CFSAUID":"G6B","PRUID":"24","PRNAME":"Quebec / Québec"},{"CFSAUID":"G6E","PRUID":"24","PRNAME":"Quebec / Québec"},{"CFSAUID":"G6G","PRUID":"24","PRNAME":"Quebec / Québec"},{"CFSAUID":"G6H","PRUID":"24","PRNAME":"Quebec / Québec"},{"CFSAUID":"G6A","PRUID":"24","PRNAME":"Quebec / Québec"},{"CFSAUID":"G8W","PRUID":"24","PRNAME":"Quebec / Québec"},{"CFSAUID":"G8Y","PRUID":"24","PRNAME":"Quebec / Québec"},{"CFSAUID":"G8Z","PRUID":"24","PRNAME":"Quebec / Québec"},{"CFSAUID":"H3Z","PRUID":"24","PRNAME":"Quebec / Québec"},{"CFSAUID":"G9C","PRUID":"24","PRNAME":"Quebec / Québec"},{"CFSAUID":"G9P","PRUID":"24","PRNAME":"Quebec / Québec"},{"CFSAUID":"H3Y","PRUID":"24","PRNAME":"Quebec / Québec"},{"CFSAUID":"G9R","PRUID":"24","PRNAME":"Quebec / Québec"},{"CFSAUID":"H1B","PRUID":"24","PRNAME":"Quebec / Québec"},{"CFSAUID":"H1J","PRUID":"24","PRNAME":"Quebec / Québec"},{"CFSAUID":"H1K","PRUID":"24","PRNAME":"Quebec / Québec"},{"CFSAUID":"H1L","PRUID":"24","PRNAME":"Quebec / Québec"},{"CFSAUID":"H1M","PRUID":"24","PRNAME":"Quebec / Québec"},{"CFSAUID":"H1N","PRUID":"24","PRNAME":"Quebec / Québec"},{"CFSAUID":"H1P","PRUID":"24","PRNAME":"Quebec / Québec"},{"CFSAUID":"H1R","PRUID":"24","PRNAME":"Quebec / Québec"},{"CFSAUID":"H1S","PRUID":"24","PRNAME":"Quebec / Québec"},{"CFSAUID":"H1T","PRUID":"24","PRNAME":"Quebec / Québec"},{"CFSAUID":"H1V","PRUID":"24","PRNAME":"Quebec / Québec"},{"CFSAUID":"H1W","PRUID":"24","PRNAME":"Quebec / Québec"},{"CFSAUID":"H1X","PRUID":"24","PRNAME":"Quebec / Québec"},{"CFSAUID":"H1Y","PRUID":"24","PRNAME":"Quebec / Québec"},{"CFSAUID":"H1Z","PRUID":"24","PRNAME":"Quebec / Québec"},{"CFSAUID":"H2A","PRUID":"24","PRNAME":"Quebec / Québec"},{"CFSAUID":"H1C","PRUID":"24","PRNAME":"Quebec / Québec"},{"CFSAUID":"H1E","PRUID":"24","PRNAME":"Quebec / Québec"},{"CFSAUID":"H1G","PRUID":"24","PRNAME":"Quebec / Québec"},{"CFSAUID":"H1H","PRUID":"24","PRNAME":"Quebec / Québec"},{"CFSAUID":"H3H","PRUID":"24","PRNAME":"Quebec / Québec"},{"CFSAUID":"H3J","PRUID":"24","PRNAME":"Quebec / Québec"},{"CFSAUID":"H3K","PRUID":"24","PRNAME":"Quebec / Québec"},{"CFSAUID":"H3L","PRUID":"24","PRNAME":"Quebec / Québec"},{"CFSAUID":"H3M","PRUID":"24","PRNAME":"Quebec / Québec"},{"CFSAUID":"H3N","PRUID":"24","PRNAME":"Quebec / Québec"},{"CFSAUID":"H3P","PRUID":"24","PRNAME":"Quebec / Québec"},{"CFSAUID":"H3R","PRUID":"24","PRNAME":"Quebec / Québec"},{"CFSAUID":"H3S","PRUID":"24","PRNAME":"Quebec / Québec"},{"CFSAUID":"H3T","PRUID":"24","PRNAME":"Quebec / Québec"},{"CFSAUID":"H3V","PRUID":"24","PRNAME":"Quebec / Québec"},{"CFSAUID":"H3W","PRUID":"24","PRNAME":"Quebec / Québec"},{"CFSAUID":"H3X","PRUID":"24","PRNAME":"Quebec / Québec"},{"CFSAUID":"H7H","PRUID":"24","PRNAME":"Quebec / Québec"},{"CFSAUID":"H7J","PRUID":"24","PRNAME":"Quebec / Québec"},{"CFSAUID":"H7K","PRUID":"24","PRNAME":"Quebec / Québec"},{"CFSAUID":"H7N","PRUID":"24","PRNAME":"Quebec / Québec"},{"CFSAUID":"H7P","PRUID":"24","PRNAME":"Quebec / Québec"},{"CFSAUID":"H7R","PRUID":"24","PRNAME":"Quebec / Québec"},{"CFSAUID":"H4A","PRUID":"24","PRNAME":"Quebec / Québec"},{"CFSAUID":"H4B","PRUID":"24","PRNAME":"Quebec / Québec"},{"CFSAUID":"H4C","PRUID":"24","PRNAME":"Quebec / Québec"},{"CFSAUID":"H4E","PRUID":"24","PRNAME":"Quebec / Québec"},{"CFSAUID":"H4G","PRUID":"24","PRNAME":"Quebec / Québec"},{"CFSAUID":"H4H","PRUID":"24","PRNAME":"Quebec / Québec"},{"CFSAUID":"H4J","PRUID":"24","PRNAME":"Quebec / Québec"},{"CFSAUID":"H4K","PRUID":"24","PRNAME":"Quebec / Québec"},{"CFSAUID":"H4L","PRUID":"24","PRNAME":"Quebec / Québec"},{"CFSAUID":"H4M","PRUID":"24","PRNAME":"Quebec / Québec"},{"CFSAUID":"H4N","PRUID":"24","PRNAME":"Quebec / Québec"},{"CFSAUID":"H4P","PRUID":"24","PRNAME":"Quebec / Québec"},{"CFSAUID":"H2B","PRUID":"24","PRNAME":"Quebec / Québec"},{"CFSAUID":"H2C","PRUID":"24","PRNAME":"Quebec / Québec"},{"CFSAUID":"H2E","PRUID":"24","PRNAME":"Quebec / Québec"},{"CFSAUID":"H2G","PRUID":"24","PRNAME":"Quebec / Québec"},{"CFSAUID":"H2H","PRUID":"24","PRNAME":"Quebec / Québec"},{"CFSAUID":"H2J","PRUID":"24","PRNAME":"Quebec / Québec"},{"CFSAUID":"H2K","PRUID":"24","PRNAME":"Quebec / Québec"},{"CFSAUID":"H2L","PRUID":"24","PRNAME":"Quebec / Québec"},{"CFSAUID":"H2M","PRUID":"24","PRNAME":"Quebec / Québec"},{"CFSAUID":"H2N","PRUID":"24","PRNAME":"Quebec / Québec"},{"CFSAUID":"H2P","PRUID":"24","PRNAME":"Quebec / Québec"},{"CFSAUID":"H2R","PRUID":"24","PRNAME":"Quebec / Québec"},{"CFSAUID":"H2S","PRUID":"24","PRNAME":"Quebec / Québec"},{"CFSAUID":"H2T","PRUID":"24","PRNAME":"Quebec / Québec"},{"CFSAUID":"H2V","PRUID":"24","PRNAME":"Quebec / Québec"},{"CFSAUID":"H2W","PRUID":"24","PRNAME":"Quebec / Québec"},{"CFSAUID":"H2X","PRUID":"24","PRNAME":"Quebec / Québec"},{"CFSAUID":"H2Y","PRUID":"24","PRNAME":"Quebec / Québec"},{"CFSAUID":"H2Z","PRUID":"24","PRNAME":"Quebec / Québec"},{"CFSAUID":"H3A","PRUID":"24","PRNAME":"Quebec / Québec"},{"CFSAUID":"H3B","PRUID":"24","PRNAME":"Quebec / Québec"},{"CFSAUID":"H3C","PRUID":"24","PRNAME":"Quebec / Québec"},{"CFSAUID":"H3E","PRUID":"24","PRNAME":"Quebec / Québec"},{"CFSAUID":"H3G","PRUID":"24","PRNAME":"Quebec / Québec"},{"CFSAUID":"H7B","PRUID":"24","PRNAME":"Quebec / Québec"},{"CFSAUID":"H7E","PRUID":"24","PRNAME":"Quebec / Québec"},{"CFSAUID":"H7G","PRUID":"24","PRNAME":"Quebec / Québec"},{"CFSAUID":"J1E","PRUID":"24","PRNAME":"Quebec / Québec"},{"CFSAUID":"J1G","PRUID":"24","PRNAME":"Quebec / Québec"},{"CFSAUID":"J1H","PRUID":"24","PRNAME":"Quebec / Québec"},{"CFSAUID":"J1M","PRUID":"24","PRNAME":"Quebec / Québec"},{"CFSAUID":"H7S","PRUID":"24","PRNAME":"Quebec / Québec"},{"CFSAUID":"H7T","PRUID":"24","PRNAME":"Quebec / Québec"},{"CFSAUID":"H7V","PRUID":"24","PRNAME":"Quebec / Québec"},{"CFSAUID":"H7W","PRUID":"24","PRNAME":"Quebec / Québec"},{"CFSAUID":"H7X","PRUID":"24","PRNAME":"Quebec / Québec"},{"CFSAUID":"H7Y","PRUID":"24","PRNAME":"Quebec / Québec"},{"CFSAUID":"H8N","PRUID":"24","PRNAME":"Quebec / Québec"},{"CFSAUID":"H7L","PRUID":"24","PRNAME":"Quebec / Québec"},{"CFSAUID":"H7M","PRUID":"24","PRNAME":"Quebec / Québec"},{"CFSAUID":"H4R","PRUID":"24","PRNAME":"Quebec / Québec"},{"CFSAUID":"H4S","PRUID":"24","PRNAME":"Quebec / Québec"},{"CFSAUID":"H4V","PRUID":"24","PRNAME":"Quebec / Québec"},{"CFSAUID":"H4W","PRUID":"24","PRNAME":"Quebec / Québec"},{"CFSAUID":"H4X","PRUID":"24","PRNAME":"Quebec / Québec"},{"CFSAUID":"H7A","PRUID":"24","PRNAME":"Quebec / Québec"},{"CFSAUID":"H7C","PRUID":"24","PRNAME":"Quebec / Québec"},{"CFSAUID":"H9P","PRUID":"24","PRNAME":"Quebec / Québec"},{"CFSAUID":"H9R","PRUID":"24","PRNAME":"Quebec / Québec"},{"CFSAUID":"H9S","PRUID":"24","PRNAME":"Quebec / Québec"},{"CFSAUID":"H9W","PRUID":"24","PRNAME":"Quebec / Québec"},{"CFSAUID":"H9X","PRUID":"24","PRNAME":"Quebec / Québec"},{"CFSAUID":"J0A","PRUID":"24","PRNAME":"Quebec / Québec"},{"CFSAUID":"J0B","PRUID":"24","PRNAME":"Quebec / Québec"},{"CFSAUID":"J0C","PRUID":"24","PRNAME":"Quebec / Québec"},{"CFSAUID":"J0E","PRUID":"24","PRNAME":"Quebec / Québec"},{"CFSAUID":"J0G","PRUID":"24","PRNAME":"Quebec / Québec"},{"CFSAUID":"J0H","PRUID":"24","PRNAME":"Quebec / Québec"},{"CFSAUID":"J0J","PRUID":"24","PRNAME":"Quebec / Québec"},{"CFSAUID":"J0K","PRUID":"24","PRNAME":"Quebec / Québec"},{"CFSAUID":"J0L","PRUID":"24","PRNAME":"Quebec / Québec"},{"CFSAUID":"J0M","PRUID":"24","PRNAME":"Quebec / Québec"},{"CFSAUID":"J0N","PRUID":"24","PRNAME":"Quebec / Québec"},{"CFSAUID":"J0P","PRUID":"24","PRNAME":"Quebec / Québec"},{"CFSAUID":"J0R","PRUID":"24","PRNAME":"Quebec / Québec"},{"CFSAUID":"J0S","PRUID":"24","PRNAME":"Quebec / Québec"},{"CFSAUID":"J0T","PRUID":"24","PRNAME":"Quebec / Québec"},{"CFSAUID":"J0V","PRUID":"24","PRNAME":"Quebec / Québec"},{"CFSAUID":"J0W","PRUID":"24","PRNAME":"Quebec / Québec"},{"CFSAUID":"J0X","PRUID":"24","PRNAME":"Quebec / Québec"},{"CFSAUID":"J0Y","PRUID":"24","PRNAME":"Quebec / Québec"},{"CFSAUID":"J0Z","PRUID":"24","PRNAME":"Quebec / Québec"},{"CFSAUID":"J1A","PRUID":"24","PRNAME":"Quebec / Québec"},{"CFSAUID":"J1C","PRUID":"24","PRNAME":"Quebec / Québec"},{"CFSAUID":"J2K","PRUID":"24","PRNAME":"Quebec / Québec"},{"CFSAUID":"J2M","PRUID":"24","PRNAME":"Quebec / Québec"},{"CFSAUID":"J2N","PRUID":"24","PRNAME":"Quebec / Québec"},{"CFSAUID":"J1J","PRUID":"24","PRNAME":"Quebec / Québec"},{"CFSAUID":"J1K","PRUID":"24","PRNAME":"Quebec / Québec"},{"CFSAUID":"J1L","PRUID":"24","PRNAME":"Quebec / Québec"},{"CFSAUID":"J1N","PRUID":"24","PRNAME":"Quebec / Québec"},{"CFSAUID":"J1R","PRUID":"24","PRNAME":"Quebec / Québec"},{"CFSAUID":"J1S","PRUID":"24","PRNAME":"Quebec / Québec"},{"CFSAUID":"J1T","PRUID":"24","PRNAME":"Quebec / Québec"},{"CFSAUID":"J1X","PRUID":"24","PRNAME":"Quebec / Québec"},{"CFSAUID":"H8S","PRUID":"24","PRNAME":"Quebec / Québec"},{"CFSAUID":"H8P","PRUID":"24","PRNAME":"Quebec / Québec"},{"CFSAUID":"H8R","PRUID":"24","PRNAME":"Quebec / Québec"},{"CFSAUID":"H8T","PRUID":"24","PRNAME":"Quebec / Québec"},{"CFSAUID":"H8Y","PRUID":"24","PRNAME":"Quebec / Québec"},{"CFSAUID":"H8Z","PRUID":"24","PRNAME":"Quebec / Québec"},{"CFSAUID":"H9A","PRUID":"24","PRNAME":"Quebec / Québec"},{"CFSAUID":"H9B","PRUID":"24","PRNAME":"Quebec / Québec"},{"CFSAUID":"H9C","PRUID":"24","PRNAME":"Quebec / Québec"},{"CFSAUID":"H9E","PRUID":"24","PRNAME":"Quebec / Québec"},{"CFSAUID":"H9G","PRUID":"24","PRNAME":"Quebec / Québec"},{"CFSAUID":"H9H","PRUID":"24","PRNAME":"Quebec / Québec"},{"CFSAUID":"H9J","PRUID":"24","PRNAME":"Quebec / Québec"},{"CFSAUID":"H9K","PRUID":"24","PRNAME":"Quebec / Québec"},{"CFSAUID":"J2C","PRUID":"24","PRNAME":"Quebec / Québec"},{"CFSAUID":"J2E","PRUID":"24","PRNAME":"Quebec / Québec"},{"CFSAUID":"J2G","PRUID":"24","PRNAME":"Quebec / Québec"},{"CFSAUID":"J2H","PRUID":"24","PRNAME":"Quebec / Québec"},{"CFSAUID":"J2J","PRUID":"24","PRNAME":"Quebec / Québec"},{"CFSAUID":"J2L","PRUID":"24","PRNAME":"Quebec / Québec"},{"CFSAUID":"J2R","PRUID":"24","PRNAME":"Quebec / Québec"},{"CFSAUID":"J2T","PRUID":"24","PRNAME":"Quebec / Québec"},{"CFSAUID":"J3B","PRUID":"24","PRNAME":"Quebec / Québec"},{"CFSAUID":"J4H","PRUID":"24","PRNAME":"Quebec / Québec"},{"CFSAUID":"J4J","PRUID":"24","PRNAME":"Quebec / Québec"},{"CFSAUID":"J4K","PRUID":"24","PRNAME":"Quebec / Québec"},{"CFSAUID":"J4L","PRUID":"24","PRNAME":"Quebec / Québec"},{"CFSAUID":"J2S","PRUID":"24","PRNAME":"Quebec / Québec"},{"CFSAUID":"J2W","PRUID":"24","PRNAME":"Quebec / Québec"},{"CFSAUID":"J2X","PRUID":"24","PRNAME":"Quebec / Québec"},{"CFSAUID":"J2Y","PRUID":"24","PRNAME":"Quebec / Québec"},{"CFSAUID":"J3A","PRUID":"24","PRNAME":"Quebec / Québec"},{"CFSAUID":"J3E","PRUID":"24","PRNAME":"Quebec / Québec"},{"CFSAUID":"J3G","PRUID":"24","PRNAME":"Quebec / Québec"},{"CFSAUID":"J3H","PRUID":"24","PRNAME":"Quebec / Québec"},{"CFSAUID":"J3L","PRUID":"24","PRNAME":"Quebec / Québec"},{"CFSAUID":"J3M","PRUID":"24","PRNAME":"Quebec / Québec"},{"CFSAUID":"J3N","PRUID":"24","PRNAME":"Quebec / Québec"},{"CFSAUID":"J3P","PRUID":"24","PRNAME":"Quebec / Québec"},{"CFSAUID":"J3R","PRUID":"24","PRNAME":"Quebec / Québec"},{"CFSAUID":"J3T","PRUID":"24","PRNAME":"Quebec / Québec"},{"CFSAUID":"J3X","PRUID":"24","PRNAME":"Quebec / Québec"},{"CFSAUID":"J4B","PRUID":"24","PRNAME":"Quebec / Québec"},{"CFSAUID":"J4G","PRUID":"24","PRNAME":"Quebec / Québec"},{"CFSAUID":"J3V","PRUID":"24","PRNAME":"Quebec / Québec"},{"CFSAUID":"J3Y","PRUID":"24","PRNAME":"Quebec / Québec"},{"CFSAUID":"J3Z","PRUID":"24","PRNAME":"Quebec / Québec"},{"CFSAUID":"J1Z","PRUID":"24","PRNAME":"Quebec / Québec"},{"CFSAUID":"J2A","PRUID":"24","PRNAME":"Quebec / Québec"},{"CFSAUID":"J2B","PRUID":"24","PRNAME":"Quebec / Québec"},{"CFSAUID":"J5T","PRUID":"24","PRNAME":"Quebec / Québec"},{"CFSAUID":"J5V","PRUID":"24","PRNAME":"Quebec / Québec"},{"CFSAUID":"J5Y","PRUID":"24","PRNAME":"Quebec / Québec"},{"CFSAUID":"J5Z","PRUID":"24","PRNAME":"Quebec / Québec"},{"CFSAUID":"J6Z","PRUID":"24","PRNAME":"Quebec / Québec"},{"CFSAUID":"J7B","PRUID":"24","PRNAME":"Quebec / Québec"},{"CFSAUID":"J7C","PRUID":"24","PRNAME":"Quebec / Québec"},{"CFSAUID":"J7E","PRUID":"24","PRNAME":"Quebec / Québec"},{"CFSAUID":"J7G","PRUID":"24","PRNAME":"Quebec / Québec"},{"CFSAUID":"J7J","PRUID":"24","PRNAME":"Quebec / Québec"},{"CFSAUID":"J7N","PRUID":"24","PRNAME":"Quebec / Québec"},{"CFSAUID":"J7P","PRUID":"24","PRNAME":"Quebec / Québec"},{"CFSAUID":"J7R","PRUID":"24","PRNAME":"Quebec / Québec"},{"CFSAUID":"J7T","PRUID":"24","PRNAME":"Quebec / Québec"},{"CFSAUID":"J7V","PRUID":"24","PRNAME":"Quebec / Québec"},{"CFSAUID":"J7H","PRUID":"24","PRNAME":"Quebec / Québec"},{"CFSAUID":"J4M","PRUID":"24","PRNAME":"Quebec / Québec"},{"CFSAUID":"J4N","PRUID":"24","PRNAME":"Quebec / Québec"},{"CFSAUID":"J4P","PRUID":"24","PRNAME":"Quebec / Québec"},{"CFSAUID":"J4R","PRUID":"24","PRNAME":"Quebec / Québec"},{"CFSAUID":"J4S","PRUID":"24","PRNAME":"Quebec / Québec"},{"CFSAUID":"J4T","PRUID":"24","PRNAME":"Quebec / Québec"},{"CFSAUID":"J4V","PRUID":"24","PRNAME":"Quebec / Québec"},{"CFSAUID":"J4W","PRUID":"24","PRNAME":"Quebec / Québec"},{"CFSAUID":"J4X","PRUID":"24","PRNAME":"Quebec / Québec"},{"CFSAUID":"J4Y","PRUID":"24","PRNAME":"Quebec / Québec"},{"CFSAUID":"J4Z","PRUID":"24","PRNAME":"Quebec / Québec"},{"CFSAUID":"J5A","PRUID":"24","PRNAME":"Quebec / Québec"},{"CFSAUID":"J5B","PRUID":"24","PRNAME":"Quebec / Québec"},{"CFSAUID":"J5C","PRUID":"24","PRNAME":"Quebec / Québec"},{"CFSAUID":"J5J","PRUID":"24","PRNAME":"Quebec / Québec"},{"CFSAUID":"J5K","PRUID":"24","PRNAME":"Quebec / Québec"},{"CFSAUID":"J5L","PRUID":"24","PRNAME":"Quebec / Québec"},{"CFSAUID":"J5M","PRUID":"24","PRNAME":"Quebec / Québec"},{"CFSAUID":"J5R","PRUID":"24","PRNAME":"Quebec / Québec"},{"CFSAUID":"J5W","PRUID":"24","PRNAME":"Quebec / Québec"},{"CFSAUID":"J5X","PRUID":"24","PRNAME":"Quebec / Québec"},{"CFSAUID":"J6A","PRUID":"24","PRNAME":"Quebec / Québec"},{"CFSAUID":"L1J","PRUID":"35","PRNAME":"Ontario"},{"CFSAUID":"L1N","PRUID":"35","PRNAME":"Ontario"},{"CFSAUID":"J7A","PRUID":"24","PRNAME":"Quebec / Québec"},{"CFSAUID":"J6K","PRUID":"24","PRNAME":"Quebec / Québec"},{"CFSAUID":"J6N","PRUID":"24","PRNAME":"Quebec / Québec"},{"CFSAUID":"J6R","PRUID":"24","PRNAME":"Quebec / Québec"},{"CFSAUID":"J6S","PRUID":"24","PRNAME":"Quebec / Québec"},{"CFSAUID":"J6T","PRUID":"24","PRNAME":"Quebec / Québec"},{"CFSAUID":"J6V","PRUID":"24","PRNAME":"Quebec / Québec"},{"CFSAUID":"J6W","PRUID":"24","PRNAME":"Quebec / Québec"},{"CFSAUID":"J6X","PRUID":"24","PRNAME":"Quebec / Québec"},{"CFSAUID":"J6Y","PRUID":"24","PRNAME":"Quebec / Québec"},{"CFSAUID":"J9H","PRUID":"24","PRNAME":"Quebec / Québec"},{"CFSAUID":"J9J","PRUID":"24","PRNAME":"Quebec / Québec"},{"CFSAUID":"J9L","PRUID":"24","PRNAME":"Quebec / Québec"},{"CFSAUID":"J9P","PRUID":"24","PRNAME":"Quebec / Québec"},{"CFSAUID":"J9T","PRUID":"24","PRNAME":"Quebec / Québec"},{"CFSAUID":"J7K","PRUID":"24","PRNAME":"Quebec / Québec"},{"CFSAUID":"J7L","PRUID":"24","PRNAME":"Quebec / Québec"},{"CFSAUID":"J7M","PRUID":"24","PRNAME":"Quebec / Québec"},{"CFSAUID":"J7W","PRUID":"24","PRNAME":"Quebec / Québec"},{"CFSAUID":"J7X","PRUID":"24","PRNAME":"Quebec / Québec"},{"CFSAUID":"J7Y","PRUID":"24","PRNAME":"Quebec / Québec"},{"CFSAUID":"J7Z","PRUID":"24","PRNAME":"Quebec / Québec"},{"CFSAUID":"J8A","PRUID":"24","PRNAME":"Quebec / Québec"},{"CFSAUID":"J8B","PRUID":"24","PRNAME":"Quebec / Québec"},{"CFSAUID":"J8C","PRUID":"24","PRNAME":"Quebec / Québec"},{"CFSAUID":"J6E","PRUID":"24","PRNAME":"Quebec / Québec"},{"CFSAUID":"J6J","PRUID":"24","PRNAME":"Quebec / Québec"},{"CFSAUID":"J8X","PRUID":"24","PRNAME":"Quebec / Québec"},{"CFSAUID":"J8Y","PRUID":"24","PRNAME":"Quebec / Québec"},{"CFSAUID":"J8Z","PRUID":"24","PRNAME":"Quebec / Québec"},{"CFSAUID":"J9A","PRUID":"24","PRNAME":"Quebec / Québec"},{"CFSAUID":"J9B","PRUID":"24","PRNAME":"Quebec / Québec"},{"CFSAUID":"J9E","PRUID":"24","PRNAME":"Quebec / Québec"},{"CFSAUID":"K1R","PRUID":"35","PRNAME":"Ontario"},{"CFSAUID":"K1S","PRUID":"35","PRNAME":"Ontario"},{"CFSAUID":"K1T","PRUID":"35","PRNAME":"Ontario"},{"CFSAUID":"K1V","PRUID":"35","PRNAME":"Ontario"},{"CFSAUID":"J9V","PRUID":"24","PRNAME":"Quebec / Québec"},{"CFSAUID":"J9X","PRUID":"24","PRNAME":"Quebec / Québec"},{"CFSAUID":"J9Y","PRUID":"24","PRNAME":"Quebec / Québec"},{"CFSAUID":"J9Z","PRUID":"24","PRNAME":"Quebec / Québec"},{"CFSAUID":"K0A","PRUID":"35","PRNAME":"Ontario"},{"CFSAUID":"K0B","PRUID":"35","PRNAME":"Ontario"},{"CFSAUID":"K0C","PRUID":"35","PRNAME":"Ontario"},{"CFSAUID":"K0E","PRUID":"35","PRNAME":"Ontario"},{"CFSAUID":"K0G","PRUID":"35","PRNAME":"Ontario"},{"CFSAUID":"K0H","PRUID":"35","PRNAME":"Ontario"},{"CFSAUID":"K0J","PRUID":"35","PRNAME":"Ontario"},{"CFSAUID":"K0K","PRUID":"35","PRNAME":"Ontario"},{"CFSAUID":"K0L","PRUID":"35","PRNAME":"Ontario"},{"CFSAUID":"K0M","PRUID":"35","PRNAME":"Ontario"},{"CFSAUID":"K1B","PRUID":"35","PRNAME":"Ontario"},{"CFSAUID":"K1C","PRUID":"35","PRNAME":"Ontario"},{"CFSAUID":"K1E","PRUID":"35","PRNAME":"Ontario"},{"CFSAUID":"J8E","PRUID":"24","PRNAME":"Quebec / Québec"},{"CFSAUID":"J8G","PRUID":"24","PRNAME":"Quebec / Québec"},{"CFSAUID":"J8H","PRUID":"24","PRNAME":"Quebec / Québec"},{"CFSAUID":"J8L","PRUID":"24","PRNAME":"Quebec / Québec"},{"CFSAUID":"J8M","PRUID":"24","PRNAME":"Quebec / Québec"},{"CFSAUID":"J8N","PRUID":"24","PRNAME":"Quebec / Québec"},{"CFSAUID":"J8R","PRUID":"24","PRNAME":"Quebec / Québec"},{"CFSAUID":"J8V","PRUID":"24","PRNAME":"Quebec / Québec"},{"CFSAUID":"J8P","PRUID":"24","PRNAME":"Quebec / Québec"},{"CFSAUID":"J8T","PRUID":"24","PRNAME":"Quebec / Québec"},{"CFSAUID":"K1K","PRUID":"35","PRNAME":"Ontario"},{"CFSAUID":"K1L","PRUID":"35","PRNAME":"Ontario"},{"CFSAUID":"K1M","PRUID":"35","PRNAME":"Ontario"},{"CFSAUID":"K1N","PRUID":"35","PRNAME":"Ontario"},{"CFSAUID":"K1P","PRUID":"35","PRNAME":"Ontario"},{"CFSAUID":"K8P","PRUID":"35","PRNAME":"Ontario"},{"CFSAUID":"K8R","PRUID":"35","PRNAME":"Ontario"},{"CFSAUID":"K1W","PRUID":"35","PRNAME":"Ontario"},{"CFSAUID":"K1X","PRUID":"35","PRNAME":"Ontario"},{"CFSAUID":"K1Y","PRUID":"35","PRNAME":"Ontario"},{"CFSAUID":"K1Z","PRUID":"35","PRNAME":"Ontario"},{"CFSAUID":"K2A","PRUID":"35","PRNAME":"Ontario"},{"CFSAUID":"K2B","PRUID":"35","PRNAME":"Ontario"},{"CFSAUID":"K2C","PRUID":"35","PRNAME":"Ontario"},{"CFSAUID":"K2E","PRUID":"35","PRNAME":"Ontario"},{"CFSAUID":"K2G","PRUID":"35","PRNAME":"Ontario"},{"CFSAUID":"K2H","PRUID":"35","PRNAME":"Ontario"},{"CFSAUID":"K2J","PRUID":"35","PRNAME":"Ontario"},{"CFSAUID":"K2K","PRUID":"35","PRNAME":"Ontario"},{"CFSAUID":"K2L","PRUID":"35","PRNAME":"Ontario"},{"CFSAUID":"K2M","PRUID":"35","PRNAME":"Ontario"},{"CFSAUID":"K2P","PRUID":"35","PRNAME":"Ontario"},{"CFSAUID":"K2R","PRUID":"35","PRNAME":"Ontario"},{"CFSAUID":"K1G","PRUID":"35","PRNAME":"Ontario"},{"CFSAUID":"K1H","PRUID":"35","PRNAME":"Ontario"},{"CFSAUID":"K1J","PRUID":"35","PRNAME":"Ontario"},{"CFSAUID":"K6K","PRUID":"35","PRNAME":"Ontario"},{"CFSAUID":"K6T","PRUID":"35","PRNAME":"Ontario"},{"CFSAUID":"K6V","PRUID":"35","PRNAME":"Ontario"},{"CFSAUID":"K7A","PRUID":"35","PRNAME":"Ontario"},{"CFSAUID":"K7C","PRUID":"35","PRNAME":"Ontario"},{"CFSAUID":"K7G","PRUID":"35","PRNAME":"Ontario"},{"CFSAUID":"K7H","PRUID":"35","PRNAME":"Ontario"},{"CFSAUID":"K7K","PRUID":"35","PRNAME":"Ontario"},{"CFSAUID":"K7L","PRUID":"35","PRNAME":"Ontario"},{"CFSAUID":"K7M","PRUID":"35","PRNAME":"Ontario"},{"CFSAUID":"K7N","PRUID":"35","PRNAME":"Ontario"},{"CFSAUID":"K7P","PRUID":"35","PRNAME":"Ontario"},{"CFSAUID":"K7R","PRUID":"35","PRNAME":"Ontario"},{"CFSAUID":"K7S","PRUID":"35","PRNAME":"Ontario"},{"CFSAUID":"K7V","PRUID":"35","PRNAME":"Ontario"},{"CFSAUID":"K8A","PRUID":"35","PRNAME":"Ontario"},{"CFSAUID":"K8B","PRUID":"35","PRNAME":"Ontario"},{"CFSAUID":"K8H","PRUID":"35","PRNAME":"Ontario"},{"CFSAUID":"K8N","PRUID":"35","PRNAME":"Ontario"},{"CFSAUID":"K8V","PRUID":"35","PRNAME":"Ontario"},{"CFSAUID":"K9A","PRUID":"35","PRNAME":"Ontario"},{"CFSAUID":"K9J","PRUID":"35","PRNAME":"Ontario"},{"CFSAUID":"K9V","PRUID":"35","PRNAME":"Ontario"},{"CFSAUID":"L0A","PRUID":"35","PRNAME":"Ontario"},{"CFSAUID":"L0B","PRUID":"35","PRNAME":"Ontario"},{"CFSAUID":"L0C","PRUID":"35","PRNAME":"Ontario"},{"CFSAUID":"L0E","PRUID":"35","PRNAME":"Ontario"},{"CFSAUID":"L0G","PRUID":"35","PRNAME":"Ontario"},{"CFSAUID":"L0H","PRUID":"35","PRNAME":"Ontario"},{"CFSAUID":"L0K","PRUID":"35","PRNAME":"Ontario"},{"CFSAUID":"L0L","PRUID":"35","PRNAME":"Ontario"},{"CFSAUID":"L0M","PRUID":"35","PRNAME":"Ontario"},{"CFSAUID":"L0N","PRUID":"35","PRNAME":"Ontario"},{"CFSAUID":"L0P","PRUID":"35","PRNAME":"Ontario"},{"CFSAUID":"S7H","PRUID":"47","PRNAME":"Saskatchewan"},{"CFSAUID":"S7J","PRUID":"47","PRNAME":"Saskatchewan"},{"CFSAUID":"S7K","PRUID":"47","PRNAME":"Saskatchewan"},{"CFSAUID":"S7L","PRUID":"47","PRNAME":"Saskatchewan"},{"CFSAUID":"T5G","PRUID":"48","PRNAME":"Alberta"},{"CFSAUID":"K9H","PRUID":"35","PRNAME":"Ontario"},{"CFSAUID":"K9K","PRUID":"35","PRNAME":"Ontario"},{"CFSAUID":"K9L","PRUID":"35","PRNAME":"Ontario"},{"CFSAUID":"L0J","PRUID":"35","PRNAME":"Ontario"},{"CFSAUID":"L0R","PRUID":"35","PRNAME":"Ontario"},{"CFSAUID":"L0S","PRUID":"35","PRNAME":"Ontario"},{"CFSAUID":"L1A","PRUID":"35","PRNAME":"Ontario"},{"CFSAUID":"L1B","PRUID":"35","PRNAME":"Ontario"},{"CFSAUID":"L1C","PRUID":"35","PRNAME":"Ontario"},{"CFSAUID":"L1E","PRUID":"35","PRNAME":"Ontario"},{"CFSAUID":"L1G","PRUID":"35","PRNAME":"Ontario"},{"CFSAUID":"L1H","PRUID":"35","PRNAME":"Ontario"},{"CFSAUID":"K2S","PRUID":"35","PRNAME":"Ontario"},{"CFSAUID":"K2T","PRUID":"35","PRNAME":"Ontario"},{"CFSAUID":"K2V","PRUID":"35","PRNAME":"Ontario"},{"CFSAUID":"K2W","PRUID":"35","PRNAME":"Ontario"},{"CFSAUID":"K4A","PRUID":"35","PRNAME":"Ontario"},{"CFSAUID":"K4B","PRUID":"35","PRNAME":"Ontario"},{"CFSAUID":"K4C","PRUID":"35","PRNAME":"Ontario"},{"CFSAUID":"K4K","PRUID":"35","PRNAME":"Ontario"},{"CFSAUID":"K4M","PRUID":"35","PRNAME":"Ontario"},{"CFSAUID":"K4P","PRUID":"35","PRNAME":"Ontario"},{"CFSAUID":"K4R","PRUID":"35","PRNAME":"Ontario"},{"CFSAUID":"K6A","PRUID":"35","PRNAME":"Ontario"},{"CFSAUID":"K6H","PRUID":"35","PRNAME":"Ontario"},{"CFSAUID":"K6J","PRUID":"35","PRNAME":"Ontario"},{"CFSAUID":"L1K","PRUID":"35","PRNAME":"Ontario"},{"CFSAUID":"L1L","PRUID":"35","PRNAME":"Ontario"},{"CFSAUID":"L1M","PRUID":"35","PRNAME":"Ontario"},{"CFSAUID":"L2A","PRUID":"35","PRNAME":"Ontario"},{"CFSAUID":"L2E","PRUID":"35","PRNAME":"Ontario"},{"CFSAUID":"L2G","PRUID":"35","PRNAME":"Ontario"},{"CFSAUID":"L8G","PRUID":"35","PRNAME":"Ontario"},{"CFSAUID":"L8L","PRUID":"35","PRNAME":"Ontario"},{"CFSAUID":"L8M","PRUID":"35","PRNAME":"Ontario"},{"CFSAUID":"L8N","PRUID":"35","PRNAME":"Ontario"},{"CFSAUID":"L4X","PRUID":"35","PRNAME":"Ontario"},{"CFSAUID":"L4Y","PRUID":"35","PRNAME":"Ontario"},{"CFSAUID":"L4Z","PRUID":"35","PRNAME":"Ontario"},{"CFSAUID":"L5A","PRUID":"35","PRNAME":"Ontario"},{"CFSAUID":"N1P","PRUID":"35","PRNAME":"Ontario"},{"CFSAUID":"N1R","PRUID":"35","PRNAME":"Ontario"},{"CFSAUID":"M1P","PRUID":"35","PRNAME":"Ontario"},{"CFSAUID":"M1R","PRUID":"35","PRNAME":"Ontario"},{"CFSAUID":"M6C","PRUID":"35","PRNAME":"Ontario"},{"CFSAUID":"M6E","PRUID":"35","PRNAME":"Ontario"},{"CFSAUID":"M6G","PRUID":"35","PRNAME":"Ontario"},{"CFSAUID":"L8S","PRUID":"35","PRNAME":"Ontario"},{"CFSAUID":"L8T","PRUID":"35","PRNAME":"Ontario"},{"CFSAUID":"L8V","PRUID":"35","PRNAME":"Ontario"},{"CFSAUID":"N1S","PRUID":"35","PRNAME":"Ontario"},{"CFSAUID":"N1T","PRUID":"35","PRNAME":"Ontario"},{"CFSAUID":"N2A","PRUID":"35","PRNAME":"Ontario"},{"CFSAUID":"N2B","PRUID":"35","PRNAME":"Ontario"},{"CFSAUID":"L2M","PRUID":"35","PRNAME":"Ontario"},{"CFSAUID":"L2N","PRUID":"35","PRNAME":"Ontario"},{"CFSAUID":"L2P","PRUID":"35","PRNAME":"Ontario"},{"CFSAUID":"L2R","PRUID":"35","PRNAME":"Ontario"},{"CFSAUID":"L3B","PRUID":"35","PRNAME":"Ontario"},{"CFSAUID":"L3C","PRUID":"35","PRNAME":"Ontario"},{"CFSAUID":"L3K","PRUID":"35","PRNAME":"Ontario"},{"CFSAUID":"L3M","PRUID":"35","PRNAME":"Ontario"},{"CFSAUID":"L3P","PRUID":"35","PRNAME":"Ontario"},{"CFSAUID":"L3R","PRUID":"35","PRNAME":"Ontario"},{"CFSAUID":"L3S","PRUID":"35","PRNAME":"Ontario"},{"CFSAUID":"L3T","PRUID":"35","PRNAME":"Ontario"},{"CFSAUID":"L3V","PRUID":"35","PRNAME":"Ontario"},{"CFSAUID":"L3Y","PRUID":"35","PRNAME":"Ontario"},{"CFSAUID":"L3Z","PRUID":"35","PRNAME":"Ontario"},{"CFSAUID":"L4A","PRUID":"35","PRNAME":"Ontario"},{"CFSAUID":"L4H","PRUID":"35","PRNAME":"Ontario"},{"CFSAUID":"L4J","PRUID":"35","PRNAME":"Ontario"},{"CFSAUID":"L4K","PRUID":"35","PRNAME":"Ontario"},{"CFSAUID":"L4L","PRUID":"35","PRNAME":"Ontario"},{"CFSAUID":"L4M","PRUID":"35","PRNAME":"Ontario"},{"CFSAUID":"L4P","PRUID":"35","PRNAME":"Ontario"},{"CFSAUID":"L4R","PRUID":"35","PRNAME":"Ontario"},{"CFSAUID":"L7P","PRUID":"35","PRNAME":"Ontario"},{"CFSAUID":"L8E","PRUID":"35","PRNAME":"Ontario"},{"CFSAUID":"V8V","PRUID":"59","PRNAME":"British Columbia / Colombie-Britannique"},{"CFSAUID":"V9M","PRUID":"59","PRNAME":"British Columbia / Colombie-Britannique"},{"CFSAUID":"V9Y","PRUID":"59","PRNAME":"British Columbia / Colombie-Britannique"},{"CFSAUID":"V9Z","PRUID":"59","PRNAME":"British Columbia / Colombie-Britannique"},{"CFSAUID":"X0A","PRUID":"62","PRNAME":"Nunavut"},{"CFSAUID":"X0B","PRUID":"62","PRNAME":"Nunavut"},{"CFSAUID":"X0C","PRUID":"62","PRNAME":"Nunavut"},{"CFSAUID":"X0E","PRUID":"61","PRNAME":"Northwest Territories / Territoires du Nord-Ouest"},{"CFSAUID":"X0G","PRUID":"61","PRNAME":"Northwest Territories / Territoires du Nord-Ouest"},{"CFSAUID":"X1A","PRUID":"61","PRNAME":"Northwest Territories / Territoires du Nord-Ouest"},{"CFSAUID":"Y0A","PRUID":"60","PRNAME":"Yukon"},{"CFSAUID":"Y0B","PRUID":"60","PRNAME":"Yukon"},{"CFSAUID":"M4K","PRUID":"35","PRNAME":"Ontario"},{"CFSAUID":"M4L","PRUID":"35","PRNAME":"Ontario"},{"CFSAUID":"M4M","PRUID":"35","PRNAME":"Ontario"},{"CFSAUID":"L5V","PRUID":"35","PRNAME":"Ontario"},{"CFSAUID":"M6M","PRUID":"35","PRNAME":"Ontario"},{"CFSAUID":"M6N","PRUID":"35","PRNAME":"Ontario"},{"CFSAUID":"M6P","PRUID":"35","PRNAME":"Ontario"},{"CFSAUID":"M8W","PRUID":"35","PRNAME":"Ontario"},{"CFSAUID":"M8X","PRUID":"35","PRNAME":"Ontario"},{"CFSAUID":"M8Y","PRUID":"35","PRNAME":"Ontario"},{"CFSAUID":"M4A","PRUID":"35","PRNAME":"Ontario"},{"CFSAUID":"M4B","PRUID":"35","PRNAME":"Ontario"},{"CFSAUID":"M4C","PRUID":"35","PRNAME":"Ontario"},{"CFSAUID":"L5W","PRUID":"35","PRNAME":"Ontario"},{"CFSAUID":"N2K","PRUID":"35","PRNAME":"Ontario"},{"CFSAUID":"N2L","PRUID":"35","PRNAME":"Ontario"},{"CFSAUID":"L6S","PRUID":"35","PRNAME":"Ontario"},{"CFSAUID":"L6T","PRUID":"35","PRNAME":"Ontario"},{"CFSAUID":"L6V","PRUID":"35","PRNAME":"Ontario"},{"CFSAUID":"L6W","PRUID":"35","PRNAME":"Ontario"},{"CFSAUID":"L7E","PRUID":"35","PRNAME":"Ontario"},{"CFSAUID":"L7J","PRUID":"35","PRNAME":"Ontario"},{"CFSAUID":"L7N","PRUID":"35","PRNAME":"Ontario"},{"CFSAUID":"M9B","PRUID":"35","PRNAME":"Ontario"},{"CFSAUID":"M9C","PRUID":"35","PRNAME":"Ontario"},{"CFSAUID":"L5B","PRUID":"35","PRNAME":"Ontario"},{"CFSAUID":"L5C","PRUID":"35","PRNAME":"Ontario"},{"CFSAUID":"L5E","PRUID":"35","PRNAME":"Ontario"},{"CFSAUID":"L5G","PRUID":"35","PRNAME":"Ontario"},{"CFSAUID":"L5H","PRUID":"35","PRNAME":"Ontario"},{"CFSAUID":"L5N","PRUID":"35","PRNAME":"Ontario"},{"CFSAUID":"L9G","PRUID":"35","PRNAME":"Ontario"},{"CFSAUID":"L9H","PRUID":"35","PRNAME":"Ontario"},{"CFSAUID":"N2M","PRUID":"35","PRNAME":"Ontario"},{"CFSAUID":"N2N","PRUID":"35","PRNAME":"Ontario"},{"CFSAUID":"L9K","PRUID":"35","PRNAME":"Ontario"},{"CFSAUID":"M1S","PRUID":"35","PRNAME":"Ontario"},{"CFSAUID":"M1T","PRUID":"35","PRNAME":"Ontario"},{"CFSAUID":"M1V","PRUID":"35","PRNAME":"Ontario"},{"CFSAUID":"M2J","PRUID":"35","PRNAME":"Ontario"},{"CFSAUID":"M2M","PRUID":"35","PRNAME":"Ontario"},{"CFSAUID":"N2C","PRUID":"35","PRNAME":"Ontario"},{"CFSAUID":"N2E","PRUID":"35","PRNAME":"Ontario"},{"CFSAUID":"N2G","PRUID":"35","PRNAME":"Ontario"},{"CFSAUID":"L9L","PRUID":"35","PRNAME":"Ontario"},{"CFSAUID":"L9M","PRUID":"35","PRNAME":"Ontario"},{"CFSAUID":"L9S","PRUID":"35","PRNAME":"Ontario"},{"CFSAUID":"L9T","PRUID":"35","PRNAME":"Ontario"},{"CFSAUID":"L9V","PRUID":"35","PRNAME":"Ontario"},{"CFSAUID":"L9W","PRUID":"35","PRNAME":"Ontario"},{"CFSAUID":"L9Y","PRUID":"35","PRNAME":"Ontario"},{"CFSAUID":"M1B","PRUID":"35","PRNAME":"Ontario"},{"CFSAUID":"M1E","PRUID":"35","PRNAME":"Ontario"},{"CFSAUID":"M1G","PRUID":"35","PRNAME":"Ontario"},{"CFSAUID":"M1J","PRUID":"35","PRNAME":"Ontario"},{"CFSAUID":"M1M","PRUID":"35","PRNAME":"Ontario"},{"CFSAUID":"M2K","PRUID":"35","PRNAME":"Ontario"},{"CFSAUID":"M2L","PRUID":"35","PRNAME":"Ontario"},{"CFSAUID":"M4N","PRUID":"35","PRNAME":"Ontario"},{"CFSAUID":"L2S","PRUID":"35","PRNAME":"Ontario"},{"CFSAUID":"L2T","PRUID":"35","PRNAME":"Ontario"},{"CFSAUID":"L2V","PRUID":"35","PRNAME":"Ontario"},{"CFSAUID":"L2W","PRUID":"35","PRNAME":"Ontario"},{"CFSAUID":"L3X","PRUID":"35","PRNAME":"Ontario"},{"CFSAUID":"L4B","PRUID":"35","PRNAME":"Ontario"},{"CFSAUID":"L4C","PRUID":"35","PRNAME":"Ontario"},{"CFSAUID":"L8W","PRUID":"35","PRNAME":"Ontario"},{"CFSAUID":"L9A","PRUID":"35","PRNAME":"Ontario"},{"CFSAUID":"L9B","PRUID":"35","PRNAME":"Ontario"},{"CFSAUID":"M4P","PRUID":"35","PRNAME":"Ontario"},{"CFSAUID":"M4R","PRUID":"35","PRNAME":"Ontario"},{"CFSAUID":"M4S","PRUID":"35","PRNAME":"Ontario"},{"CFSAUID":"M4T","PRUID":"35","PRNAME":"Ontario"},{"CFSAUID":"L6A","PRUID":"35","PRNAME":"Ontario"},{"CFSAUID":"M6R","PRUID":"35","PRNAME":"Ontario"},{"CFSAUID":"M6S","PRUID":"35","PRNAME":"Ontario"},{"CFSAUID":"M8V","PRUID":"35","PRNAME":"Ontario"},{"CFSAUID":"M8Z","PRUID":"35","PRNAME":"Ontario"},{"CFSAUID":"M9A","PRUID":"35","PRNAME":"Ontario"},{"CFSAUID":"M9L","PRUID":"35","PRNAME":"Ontario"},{"CFSAUID":"M4E","PRUID":"35","PRNAME":"Ontario"},{"CFSAUID":"M4G","PRUID":"35","PRNAME":"Ontario"},{"CFSAUID":"M4H","PRUID":"35","PRNAME":"Ontario"},{"CFSAUID":"L6B","PRUID":"35","PRNAME":"Ontario"},{"CFSAUID":"V2X","PRUID":"59","PRNAME":"British Columbia / Colombie-Britannique"},{"CFSAUID":"L6X","PRUID":"35","PRNAME":"Ontario"},{"CFSAUID":"L6Y","PRUID":"35","PRNAME":"Ontario"},{"CFSAUID":"L6Z","PRUID":"35","PRNAME":"Ontario"},{"CFSAUID":"L7A","PRUID":"35","PRNAME":"Ontario"},{"CFSAUID":"L7B","PRUID":"35","PRNAME":"Ontario"},{"CFSAUID":"L7C","PRUID":"35","PRNAME":"Ontario"},{"CFSAUID":"L7G","PRUID":"35","PRNAME":"Ontario"},{"CFSAUID":"L7K","PRUID":"35","PRNAME":"Ontario"},{"CFSAUID":"L7L","PRUID":"35","PRNAME":"Ontario"},{"CFSAUID":"L7M","PRUID":"35","PRNAME":"Ontario"},{"CFSAUID":"L5J","PRUID":"35","PRNAME":"Ontario"},{"CFSAUID":"L5K","PRUID":"35","PRNAME":"Ontario"},{"CFSAUID":"L5L","PRUID":"35","PRNAME":"Ontario"},{"CFSAUID":"L5M","PRUID":"35","PRNAME":"Ontario"},{"CFSAUID":"L5R","PRUID":"35","PRNAME":"Ontario"},{"CFSAUID":"V2Y","PRUID":"59","PRNAME":"British Columbia / Colombie-Britannique"},{"CFSAUID":"V5E","PRUID":"59","PRNAME":"British Columbia / Colombie-Britannique"},{"CFSAUID":"V5G","PRUID":"59","PRNAME":"British Columbia / Colombie-Britannique"},{"CFSAUID":"M1W","PRUID":"35","PRNAME":"Ontario"},{"CFSAUID":"M1X","PRUID":"35","PRNAME":"Ontario"},{"CFSAUID":"M2H","PRUID":"35","PRNAME":"Ontario"},{"CFSAUID":"M2N","PRUID":"35","PRNAME":"Ontario"},{"CFSAUID":"M2P","PRUID":"35","PRNAME":"Ontario"},{"CFSAUID":"N2H","PRUID":"35","PRNAME":"Ontario"},{"CFSAUID":"N2J","PRUID":"35","PRNAME":"Ontario"},{"CFSAUID":"V5H","PRUID":"59","PRNAME":"British Columbia / Colombie-Britannique"},{"CFSAUID":"V8S","PRUID":"59","PRNAME":"British Columbia / Colombie-Britannique"},{"CFSAUID":"V8T","PRUID":"59","PRNAME":"British Columbia / Colombie-Britannique"},{"CFSAUID":"N2V","PRUID":"35","PRNAME":"Ontario"},{"CFSAUID":"N2Z","PRUID":"35","PRNAME":"Ontario"},{"CFSAUID":"N3A","PRUID":"35","PRNAME":"Ontario"},{"CFSAUID":"L4E","PRUID":"35","PRNAME":"Ontario"},{"CFSAUID":"L4G","PRUID":"35","PRNAME":"Ontario"},{"CFSAUID":"L9C","PRUID":"35","PRNAME":"Ontario"},{"CFSAUID":"L9J","PRUID":"35","PRNAME":"Ontario"},{"CFSAUID":"M4J","PRUID":"35","PRNAME":"Ontario"},{"CFSAUID":"L6H","PRUID":"35","PRNAME":"Ontario"},{"CFSAUID":"L6J","PRUID":"35","PRNAME":"Ontario"},{"CFSAUID":"L6K","PRUID":"35","PRNAME":"Ontario"},{"CFSAUID":"L9R","PRUID":"35","PRNAME":"Ontario"},{"CFSAUID":"L9Z","PRUID":"35","PRNAME":"Ontario"},{"CFSAUID":"M3C","PRUID":"35","PRNAME":"Ontario"},{"CFSAUID":"M3H","PRUID":"35","PRNAME":"Ontario"},{"CFSAUID":"M9M","PRUID":"35","PRNAME":"Ontario"},{"CFSAUID":"M9N","PRUID":"35","PRNAME":"Ontario"},{"CFSAUID":"M9P","PRUID":"35","PRNAME":"Ontario"},{"CFSAUID":"M3B","PRUID":"35","PRNAME":"Ontario"},{"CFSAUID":"M3L","PRUID":"35","PRNAME":"Ontario"},{"CFSAUID":"M1K","PRUID":"35","PRNAME":"Ontario"},{"CFSAUID":"M1L","PRUID":"35","PRNAME":"Ontario"},{"CFSAUID":"M1N","PRUID":"35","PRNAME":"Ontario"},{"CFSAUID":"M5A","PRUID":"35","PRNAME":"Ontario"},{"CFSAUID":"M5B","PRUID":"35","PRNAME":"Ontario"},{"CFSAUID":"M5C","PRUID":"35","PRNAME":"Ontario"},{"CFSAUID":"M5E","PRUID":"35","PRNAME":"Ontario"},{"CFSAUID":"M5G","PRUID":"35","PRNAME":"Ontario"},{"CFSAUID":"M5H","PRUID":"35","PRNAME":"Ontario"},{"CFSAUID":"M5J","PRUID":"35","PRNAME":"Ontario"},{"CFSAUID":"M5M","PRUID":"35","PRNAME":"Ontario"},{"CFSAUID":"L7R","PRUID":"35","PRNAME":"Ontario"},{"CFSAUID":"L7S","PRUID":"35","PRNAME":"Ontario"},{"CFSAUID":"L7T","PRUID":"35","PRNAME":"Ontario"},{"CFSAUID":"L8H","PRUID":"35","PRNAME":"Ontario"},{"CFSAUID":"L8J","PRUID":"35","PRNAME":"Ontario"},{"CFSAUID":"L8K","PRUID":"35","PRNAME":"Ontario"},{"CFSAUID":"L4T","PRUID":"35","PRNAME":"Ontario"},{"CFSAUID":"L4V","PRUID":"35","PRNAME":"Ontario"},{"CFSAUID":"L4W","PRUID":"35","PRNAME":"Ontario"},{"CFSAUID":"L2H","PRUID":"35","PRNAME":"Ontario"},{"CFSAUID":"L2J","PRUID":"35","PRNAME":"Ontario"},{"CFSAUID":"M6H","PRUID":"35","PRNAME":"Ontario"},{"CFSAUID":"M5V","PRUID":"35","PRNAME":"Ontario"},{"CFSAUID":"M6A","PRUID":"35","PRNAME":"Ontario"},{"CFSAUID":"M6B","PRUID":"35","PRNAME":"Ontario"},{"CFSAUID":"M2R","PRUID":"35","PRNAME":"Ontario"},{"CFSAUID":"M3A","PRUID":"35","PRNAME":"Ontario"},{"CFSAUID":"N1G","PRUID":"35","PRNAME":"Ontario"},{"CFSAUID":"N1H","PRUID":"35","PRNAME":"Ontario"},{"CFSAUID":"N1K","PRUID":"35","PRNAME":"Ontario"},{"CFSAUID":"N1L","PRUID":"35","PRNAME":"Ontario"},{"CFSAUID":"N1M","PRUID":"35","PRNAME":"Ontario"},{"CFSAUID":"M6J","PRUID":"35","PRNAME":"Ontario"},{"CFSAUID":"M6K","PRUID":"35","PRNAME":"Ontario"},{"CFSAUID":"M6L","PRUID":"35","PRNAME":"Ontario"},{"CFSAUID":"N3B","PRUID":"35","PRNAME":"Ontario"},{"CFSAUID":"N3C","PRUID":"35","PRNAME":"Ontario"},{"CFSAUID":"N3E","PRUID":"35","PRNAME":"Ontario"},{"CFSAUID":"L4N","PRUID":"35","PRNAME":"Ontario"},{"CFSAUID":"L4S","PRUID":"35","PRNAME":"Ontario"},{"CFSAUID":"L8P","PRUID":"35","PRNAME":"Ontario"},{"CFSAUID":"L8R","PRUID":"35","PRNAME":"Ontario"},{"CFSAUID":"L6L","PRUID":"35","PRNAME":"Ontario"},{"CFSAUID":"L6M","PRUID":"35","PRNAME":"Ontario"},{"CFSAUID":"L6P","PRUID":"35","PRNAME":"Ontario"},{"CFSAUID":"L6R","PRUID":"35","PRNAME":"Ontario"},{"CFSAUID":"M1C","PRUID":"35","PRNAME":"Ontario"},{"CFSAUID":"M1H","PRUID":"35","PRNAME":"Ontario"},{"CFSAUID":"M3J","PRUID":"35","PRNAME":"Ontario"},{"CFSAUID":"M3K","PRUID":"35","PRNAME":"Ontario"},{"CFSAUID":"M9R","PRUID":"35","PRNAME":"Ontario"},{"CFSAUID":"M9V","PRUID":"35","PRNAME":"Ontario"},{"CFSAUID":"M9W","PRUID":"35","PRNAME":"Ontario"},{"CFSAUID":"N0A","PRUID":"35","PRNAME":"Ontario"},{"CFSAUID":"N0B","PRUID":"35","PRNAME":"Ontario"},{"CFSAUID":"N0C","PRUID":"35","PRNAME":"Ontario"},{"CFSAUID":"N0E","PRUID":"35","PRNAME":"Ontario"},{"CFSAUID":"N0G","PRUID":"35","PRNAME":"Ontario"},{"CFSAUID":"N0H","PRUID":"35","PRNAME":"Ontario"},{"CFSAUID":"N0J","PRUID":"35","PRNAME":"Ontario"},{"CFSAUID":"N0K","PRUID":"35","PRNAME":"Ontario"},{"CFSAUID":"N0L","PRUID":"35","PRNAME":"Ontario"},{"CFSAUID":"N0M","PRUID":"35","PRNAME":"Ontario"},{"CFSAUID":"N0N","PRUID":"35","PRNAME":"Ontario"},{"CFSAUID":"N0P","PRUID":"35","PRNAME":"Ontario"},{"CFSAUID":"N0R","PRUID":"35","PRNAME":"Ontario"},{"CFSAUID":"N1A","PRUID":"35","PRNAME":"Ontario"},{"CFSAUID":"N1C","PRUID":"35","PRNAME":"Ontario"},{"CFSAUID":"N1E","PRUID":"35","PRNAME":"Ontario"},{"CFSAUID":"M3M","PRUID":"35","PRNAME":"Ontario"},{"CFSAUID":"M3N","PRUID":"35","PRNAME":"Ontario"},{"CFSAUID":"T5T","PRUID":"48","PRNAME":"Alberta"},{"CFSAUID":"T5V","PRUID":"48","PRNAME":"Alberta"},{"CFSAUID":"T5W","PRUID":"48","PRNAME":"Alberta"},{"CFSAUID":"N8M","PRUID":"35","PRNAME":"Ontario"},{"CFSAUID":"N8N","PRUID":"35","PRNAME":"Ontario"},{"CFSAUID":"N8P","PRUID":"35","PRNAME":"Ontario"},{"CFSAUID":"N5V","PRUID":"35","PRNAME":"Ontario"},{"CFSAUID":"P4R","PRUID":"35","PRNAME":"Ontario"},{"CFSAUID":"N5Y","PRUID":"35","PRNAME":"Ontario"},{"CFSAUID":"N5Z","PRUID":"35","PRNAME":"Ontario"},{"CFSAUID":"N6A","PRUID":"35","PRNAME":"Ontario"},{"CFSAUID":"N6B","PRUID":"35","PRNAME":"Ontario"},{"CFSAUID":"N9A","PRUID":"35","PRNAME":"Ontario"},{"CFSAUID":"N9B","PRUID":"35","PRNAME":"Ontario"},{"CFSAUID":"N9C","PRUID":"35","PRNAME":"Ontario"},{"CFSAUID":"P0S","PRUID":"35","PRNAME":"Ontario"},{"CFSAUID":"P0T","PRUID":"35","PRNAME":"Ontario"},{"CFSAUID":"P0V","PRUID":"35","PRNAME":"Ontario"},{"CFSAUID":"P0W","PRUID":"35","PRNAME":"Ontario"},{"CFSAUID":"P0X","PRUID":"35","PRNAME":"Ontario"},{"CFSAUID":"P0Y","PRUID":"35","PRNAME":"Ontario"},{"CFSAUID":"P1A","PRUID":"35","PRNAME":"Ontario"},{"CFSAUID":"P1B","PRUID":"35","PRNAME":"Ontario"},{"CFSAUID":"P1C","PRUID":"35","PRNAME":"Ontario"},{"CFSAUID":"P1H","PRUID":"35","PRNAME":"Ontario"},{"CFSAUID":"P1L","PRUID":"35","PRNAME":"Ontario"},{"CFSAUID":"P1P","PRUID":"35","PRNAME":"Ontario"},{"CFSAUID":"P2A","PRUID":"35","PRNAME":"Ontario"},{"CFSAUID":"P2B","PRUID":"35","PRNAME":"Ontario"},{"CFSAUID":"P2N","PRUID":"35","PRNAME":"Ontario"},{"CFSAUID":"R3V","PRUID":"46","PRNAME":"Manitoba"},{"CFSAUID":"P7E","PRUID":"35","PRNAME":"Ontario"},{"CFSAUID":"P8N","PRUID":"35","PRNAME":"Ontario"},{"CFSAUID":"P8T","PRUID":"35","PRNAME":"Ontario"},{"CFSAUID":"P9A","PRUID":"35","PRNAME":"Ontario"},{"CFSAUID":"P9N","PRUID":"35","PRNAME":"Ontario"},{"CFSAUID":"R0A","PRUID":"46","PRNAME":"Manitoba"},{"CFSAUID":"R0B","PRUID":"46","PRNAME":"Manitoba"},{"CFSAUID":"R0C","PRUID":"46","PRNAME":"Manitoba"},{"CFSAUID":"R0E","PRUID":"46","PRNAME":"Manitoba"},{"CFSAUID":"R0G","PRUID":"46","PRNAME":"Manitoba"},{"CFSAUID":"R0H","PRUID":"46","PRNAME":"Manitoba"},{"CFSAUID":"R0J","PRUID":"46","PRNAME":"Manitoba"},{"CFSAUID":"R0K","PRUID":"46","PRNAME":"Manitoba"},{"CFSAUID":"R0L","PRUID":"46","PRNAME":"Manitoba"},{"CFSAUID":"R0M","PRUID":"46","PRNAME":"Manitoba"},{"CFSAUID":"R1A","PRUID":"46","PRNAME":"Manitoba"},{"CFSAUID":"R1B","PRUID":"46","PRNAME":"Manitoba"},{"CFSAUID":"R1C","PRUID":"46","PRNAME":"Manitoba"},{"CFSAUID":"S4H","PRUID":"47","PRNAME":"Saskatchewan"},{"CFSAUID":"S4L","PRUID":"47","PRNAME":"Saskatchewan"},{"CFSAUID":"S4N","PRUID":"47","PRNAME":"Saskatchewan"},{"CFSAUID":"T4B","PRUID":"48","PRNAME":"Alberta"},{"CFSAUID":"T4C","PRUID":"48","PRNAME":"Alberta"},{"CFSAUID":"T4E","PRUID":"48","PRNAME":"Alberta"},{"CFSAUID":"R3J","PRUID":"46","PRNAME":"Manitoba"},{"CFSAUID":"R3K","PRUID":"46","PRNAME":"Manitoba"},{"CFSAUID":"R3L","PRUID":"46","PRNAME":"Manitoba"},{"CFSAUID":"R3M","PRUID":"46","PRNAME":"Manitoba"},{"CFSAUID":"T2B","PRUID":"48","PRNAME":"Alberta"},{"CFSAUID":"R3W","PRUID":"46","PRNAME":"Manitoba"},{"CFSAUID":"R3X","PRUID":"46","PRNAME":"Manitoba"},{"CFSAUID":"R3Y","PRUID":"46","PRNAME":"Manitoba"},{"CFSAUID":"R4A","PRUID":"46","PRNAME":"Manitoba"},{"CFSAUID":"T4H","PRUID":"48","PRNAME":"Alberta"},{"CFSAUID":"T4J","PRUID":"48","PRNAME":"Alberta"},{"CFSAUID":"T4L","PRUID":"48","PRNAME":"Alberta"},{"CFSAUID":"N6C","PRUID":"35","PRNAME":"Ontario"},{"CFSAUID":"T4G","PRUID":"48","PRNAME":"Alberta"},{"CFSAUID":"T5A","PRUID":"48","PRNAME":"Alberta"},{"CFSAUID":"T5B","PRUID":"48","PRNAME":"Alberta"},{"CFSAUID":"T5C","PRUID":"48","PRNAME":"Alberta"},{"CFSAUID":"T5E","PRUID":"48","PRNAME":"Alberta"},{"CFSAUID":"T2C","PRUID":"48","PRNAME":"Alberta"},{"CFSAUID":"T2E","PRUID":"48","PRNAME":"Alberta"},{"CFSAUID":"L1Y","PRUID":"35","PRNAME":"Ontario"},{"CFSAUID":"T2N","PRUID":"48","PRNAME":"Alberta"},{"CFSAUID":"T2P","PRUID":"48","PRNAME":"Alberta"},{"CFSAUID":"T2R","PRUID":"48","PRNAME":"Alberta"},{"CFSAUID":"T2S","PRUID":"48","PRNAME":"Alberta"},{"CFSAUID":"T2T","PRUID":"48","PRNAME":"Alberta"},{"CFSAUID":"N6E","PRUID":"35","PRNAME":"Ontario"},{"CFSAUID":"R1N","PRUID":"46","PRNAME":"Manitoba"},{"CFSAUID":"N6K","PRUID":"35","PRNAME":"Ontario"},{"CFSAUID":"N6M","PRUID":"35","PRNAME":"Ontario"},{"CFSAUID":"N6N","PRUID":"35","PRNAME":"Ontario"},{"CFSAUID":"L1Z","PRUID":"35","PRNAME":"Ontario"},{"CFSAUID":"N3H","PRUID":"35","PRNAME":"Ontario"},{"CFSAUID":"N9E","PRUID":"35","PRNAME":"Ontario"},{"CFSAUID":"N3S","PRUID":"35","PRNAME":"Ontario"},{"CFSAUID":"N3T","PRUID":"35","PRNAME":"Ontario"},{"CFSAUID":"N3V","PRUID":"35","PRNAME":"Ontario"},{"CFSAUID":"N3W","PRUID":"35","PRNAME":"Ontario"},{"CFSAUID":"N3Y","PRUID":"35","PRNAME":"Ontario"},{"CFSAUID":"N4G","PRUID":"35","PRNAME":"Ontario"},{"CFSAUID":"N4K","PRUID":"35","PRNAME":"Ontario"},{"CFSAUID":"N4L","PRUID":"35","PRNAME":"Ontario"},{"CFSAUID":"N4S","PRUID":"35","PRNAME":"Ontario"},{"CFSAUID":"N4T","PRUID":"35","PRNAME":"Ontario"},{"CFSAUID":"N5C","PRUID":"35","PRNAME":"Ontario"},{"CFSAUID":"N5H","PRUID":"35","PRNAME":"Ontario"},{"CFSAUID":"N5L","PRUID":"35","PRNAME":"Ontario"},{"CFSAUID":"N5P","PRUID":"35","PRNAME":"Ontario"},{"CFSAUID":"N6L","PRUID":"35","PRNAME":"Ontario"},{"CFSAUID":"N6P","PRUID":"35","PRNAME":"Ontario"},{"CFSAUID":"N7A","PRUID":"35","PRNAME":"Ontario"},{"CFSAUID":"N7M","PRUID":"35","PRNAME":"Ontario"},{"CFSAUID":"N7T","PRUID":"35","PRNAME":"Ontario"},{"CFSAUID":"R2C","PRUID":"46","PRNAME":"Manitoba"},{"CFSAUID":"S4P","PRUID":"47","PRNAME":"Saskatchewan"},{"CFSAUID":"S4R","PRUID":"47","PRNAME":"Saskatchewan"},{"CFSAUID":"S4S","PRUID":"47","PRNAME":"Saskatchewan"},{"CFSAUID":"N2P","PRUID":"35","PRNAME":"Ontario"},{"CFSAUID":"N2R","PRUID":"35","PRNAME":"Ontario"},{"CFSAUID":"N2T","PRUID":"35","PRNAME":"Ontario"},{"CFSAUID":"N9G","PRUID":"35","PRNAME":"Ontario"},{"CFSAUID":"N9H","PRUID":"35","PRNAME":"Ontario"},{"CFSAUID":"N9J","PRUID":"35","PRNAME":"Ontario"},{"CFSAUID":"N9K","PRUID":"35","PRNAME":"Ontario"},{"CFSAUID":"N9V","PRUID":"35","PRNAME":"Ontario"},{"CFSAUID":"N9Y","PRUID":"35","PRNAME":"Ontario"},{"CFSAUID":"P0A","PRUID":"35","PRNAME":"Ontario"},{"CFSAUID":"P0B","PRUID":"35","PRNAME":"Ontario"},{"CFSAUID":"P0C","PRUID":"35","PRNAME":"Ontario"},{"CFSAUID":"P0E","PRUID":"35","PRNAME":"Ontario"},{"CFSAUID":"P0G","PRUID":"35","PRNAME":"Ontario"},{"CFSAUID":"P0H","PRUID":"35","PRNAME":"Ontario"},{"CFSAUID":"P0J","PRUID":"35","PRNAME":"Ontario"},{"CFSAUID":"P0K","PRUID":"35","PRNAME":"Ontario"},{"CFSAUID":"R3N","PRUID":"46","PRNAME":"Manitoba"},{"CFSAUID":"P3A","PRUID":"35","PRNAME":"Ontario"},{"CFSAUID":"P3B","PRUID":"35","PRNAME":"Ontario"},{"CFSAUID":"P3C","PRUID":"35","PRNAME":"Ontario"},{"CFSAUID":"P3E","PRUID":"35","PRNAME":"Ontario"},{"CFSAUID":"P3L","PRUID":"35","PRNAME":"Ontario"},{"CFSAUID":"S4T","PRUID":"47","PRNAME":"Saskatchewan"},{"CFSAUID":"S4V","PRUID":"47","PRNAME":"Saskatchewan"},{"CFSAUID":"T4M","PRUID":"48","PRNAME":"Alberta"},{"CFSAUID":"T4N","PRUID":"48","PRNAME":"Alberta"},{"CFSAUID":"T4P","PRUID":"48","PRNAME":"Alberta"},{"CFSAUID":"T4R","PRUID":"48","PRNAME":"Alberta"},{"CFSAUID":"T4S","PRUID":"48","PRNAME":"Alberta"},{"CFSAUID":"M4W","PRUID":"35","PRNAME":"Ontario"},{"CFSAUID":"M4X","PRUID":"35","PRNAME":"Ontario"},{"CFSAUID":"M4Y","PRUID":"35","PRNAME":"Ontario"},{"CFSAUID":"M5N","PRUID":"35","PRNAME":"Ontario"},{"CFSAUID":"R3P","PRUID":"46","PRNAME":"Manitoba"},{"CFSAUID":"R3R","PRUID":"46","PRNAME":"Manitoba"},{"CFSAUID":"R3S","PRUID":"46","PRNAME":"Manitoba"},{"CFSAUID":"R3T","PRUID":"46","PRNAME":"Manitoba"},{"CFSAUID":"R4G","PRUID":"46","PRNAME":"Manitoba"},{"CFSAUID":"R4H","PRUID":"46","PRNAME":"Manitoba"},{"CFSAUID":"R4J","PRUID":"46","PRNAME":"Manitoba"},{"CFSAUID":"R4K","PRUID":"46","PRNAME":"Manitoba"},{"CFSAUID":"R4L","PRUID":"46","PRNAME":"Manitoba"},{"CFSAUID":"R5G","PRUID":"46","PRNAME":"Manitoba"},{"CFSAUID":"R5H","PRUID":"46","PRNAME":"Manitoba"},{"CFSAUID":"R7A","PRUID":"46","PRNAME":"Manitoba"},{"CFSAUID":"R8A","PRUID":"46","PRNAME":"Manitoba"},{"CFSAUID":"R8N","PRUID":"46","PRNAME":"Manitoba"},{"CFSAUID":"T4T","PRUID":"48","PRNAME":"Alberta"},{"CFSAUID":"T4V","PRUID":"48","PRNAME":"Alberta"},{"CFSAUID":"N6G","PRUID":"35","PRNAME":"Ontario"},{"CFSAUID":"L6C","PRUID":"35","PRNAME":"Ontario"},{"CFSAUID":"L6E","PRUID":"35","PRNAME":"Ontario"},{"CFSAUID":"L6G","PRUID":"35","PRNAME":"Ontario"},{"CFSAUID":"T2G","PRUID":"48","PRNAME":"Alberta"},{"CFSAUID":"T2H","PRUID":"48","PRNAME":"Alberta"},{"CFSAUID":"T2J","PRUID":"48","PRNAME":"Alberta"},{"CFSAUID":"T2K","PRUID":"48","PRNAME":"Alberta"},{"CFSAUID":"T2L","PRUID":"48","PRNAME":"Alberta"},{"CFSAUID":"T2M","PRUID":"48","PRNAME":"Alberta"},{"CFSAUID":"T2V","PRUID":"48","PRNAME":"Alberta"},{"CFSAUID":"T2W","PRUID":"48","PRNAME":"Alberta"},{"CFSAUID":"T2X","PRUID":"48","PRNAME":"Alberta"},{"CFSAUID":"T2Y","PRUID":"48","PRNAME":"Alberta"},{"CFSAUID":"T2Z","PRUID":"48","PRNAME":"Alberta"},{"CFSAUID":"T3A","PRUID":"48","PRNAME":"Alberta"},{"CFSAUID":"T3B","PRUID":"48","PRNAME":"Alberta"},{"CFSAUID":"T3K","PRUID":"48","PRNAME":"Alberta"},{"CFSAUID":"T3L","PRUID":"48","PRNAME":"Alberta"},{"CFSAUID":"T3Z","PRUID":"48","PRNAME":"Alberta"},{"CFSAUID":"S0A","PRUID":"47","PRNAME":"Saskatchewan"},{"CFSAUID":"S0C","PRUID":"47","PRNAME":"Saskatchewan"},{"CFSAUID":"N6H","PRUID":"35","PRNAME":"Ontario"},{"CFSAUID":"N6J","PRUID":"35","PRNAME":"Ontario"},{"CFSAUID":"R2E","PRUID":"46","PRNAME":"Manitoba"},{"CFSAUID":"R2G","PRUID":"46","PRNAME":"Manitoba"},{"CFSAUID":"L9N","PRUID":"35","PRNAME":"Ontario"},{"CFSAUID":"L9P","PRUID":"35","PRNAME":"Ontario"},{"CFSAUID":"M4V","PRUID":"35","PRNAME":"Ontario"},{"CFSAUID":"N3L","PRUID":"35","PRNAME":"Ontario"},{"CFSAUID":"N3P","PRUID":"35","PRNAME":"Ontario"},{"CFSAUID":"N3R","PRUID":"35","PRNAME":"Ontario"},{"CFSAUID":"P0L","PRUID":"35","PRNAME":"Ontario"},{"CFSAUID":"P0M","PRUID":"35","PRNAME":"Ontario"},{"CFSAUID":"P0N","PRUID":"35","PRNAME":"Ontario"},{"CFSAUID":"P0P","PRUID":"35","PRNAME":"Ontario"},{"CFSAUID":"P0R","PRUID":"35","PRNAME":"Ontario"},{"CFSAUID":"N4B","PRUID":"35","PRNAME":"Ontario"},{"CFSAUID":"N4N","PRUID":"35","PRNAME":"Ontario"},{"CFSAUID":"N4V","PRUID":"35","PRNAME":"Ontario"},{"CFSAUID":"R2H","PRUID":"46","PRNAME":"Manitoba"},{"CFSAUID":"R2J","PRUID":"46","PRNAME":"Manitoba"},{"CFSAUID":"S4W","PRUID":"47","PRNAME":"Saskatchewan"},{"CFSAUID":"S4X","PRUID":"47","PRNAME":"Saskatchewan"},{"CFSAUID":"S4Y","PRUID":"47","PRNAME":"Saskatchewan"},{"CFSAUID":"S4Z","PRUID":"47","PRNAME":"Saskatchewan"},{"CFSAUID":"S6H","PRUID":"47","PRNAME":"Saskatchewan"},{"CFSAUID":"M5P","PRUID":"35","PRNAME":"Ontario"},{"CFSAUID":"M5R","PRUID":"35","PRNAME":"Ontario"},{"CFSAUID":"M5S","PRUID":"35","PRNAME":"Ontario"},{"CFSAUID":"M5T","PRUID":"35","PRNAME":"Ontario"},{"CFSAUID":"T5H","PRUID":"48","PRNAME":"Alberta"},{"CFSAUID":"T5J","PRUID":"48","PRNAME":"Alberta"},{"CFSAUID":"T5K","PRUID":"48","PRNAME":"Alberta"},{"CFSAUID":"T5L","PRUID":"48","PRNAME":"Alberta"},{"CFSAUID":"N7G","PRUID":"35","PRNAME":"Ontario"},{"CFSAUID":"P3G","PRUID":"35","PRNAME":"Ontario"},{"CFSAUID":"P3N","PRUID":"35","PRNAME":"Ontario"},{"CFSAUID":"R5A","PRUID":"46","PRNAME":"Manitoba"},{"CFSAUID":"S6J","PRUID":"47","PRNAME":"Saskatchewan"},{"CFSAUID":"S6K","PRUID":"47","PRNAME":"Saskatchewan"},{"CFSAUID":"S6V","PRUID":"47","PRNAME":"Saskatchewan"},{"CFSAUID":"S6W","PRUID":"47","PRNAME":"Saskatchewan"},{"CFSAUID":"S6X","PRUID":"47","PRNAME":"Saskatchewan"},{"CFSAUID":"T4X","PRUID":"48","PRNAME":"Alberta"},{"CFSAUID":"N8R","PRUID":"35","PRNAME":"Ontario"},{"CFSAUID":"N8S","PRUID":"35","PRNAME":"Ontario"},{"CFSAUID":"N8T","PRUID":"35","PRNAME":"Ontario"},{"CFSAUID":"R2W","PRUID":"46","PRNAME":"Manitoba"},{"CFSAUID":"R2X","PRUID":"46","PRNAME":"Manitoba"},{"CFSAUID":"R2Y","PRUID":"46","PRNAME":"Manitoba"},{"CFSAUID":"R3A","PRUID":"46","PRNAME":"Manitoba"},{"CFSAUID":"N7L","PRUID":"35","PRNAME":"Ontario"},{"CFSAUID":"N7S","PRUID":"35","PRNAME":"Ontario"},{"CFSAUID":"N8H","PRUID":"35","PRNAME":"Ontario"},{"CFSAUID":"R2K","PRUID":"46","PRNAME":"Manitoba"},{"CFSAUID":"R6M","PRUID":"46","PRNAME":"Manitoba"},{"CFSAUID":"R6W","PRUID":"46","PRNAME":"Manitoba"},{"CFSAUID":"S0E","PRUID":"47","PRNAME":"Saskatchewan"},{"CFSAUID":"T3C","PRUID":"48","PRNAME":"Alberta"},{"CFSAUID":"P5A","PRUID":"35","PRNAME":"Ontario"},{"CFSAUID":"P5E","PRUID":"35","PRNAME":"Ontario"},{"CFSAUID":"P5N","PRUID":"35","PRNAME":"Ontario"},{"CFSAUID":"P6A","PRUID":"35","PRNAME":"Ontario"},{"CFSAUID":"R9A","PRUID":"46","PRNAME":"Manitoba"},{"CFSAUID":"S0G","PRUID":"47","PRNAME":"Saskatchewan"},{"CFSAUID":"R3B","PRUID":"46","PRNAME":"Manitoba"},{"CFSAUID":"T0P","PRUID":"48","PRNAME":"Alberta"},{"CFSAUID":"T0V","PRUID":"48","PRNAME":"Alberta"},{"CFSAUID":"T1A","PRUID":"48","PRNAME":"Alberta"},{"CFSAUID":"T1B","PRUID":"48","PRNAME":"Alberta"},{"CFSAUID":"T1C","PRUID":"48","PRNAME":"Alberta"},{"CFSAUID":"T1G","PRUID":"48","PRNAME":"Alberta"},{"CFSAUID":"T1H","PRUID":"48","PRNAME":"Alberta"},{"CFSAUID":"T1J","PRUID":"48","PRNAME":"Alberta"},{"CFSAUID":"T1K","PRUID":"48","PRNAME":"Alberta"},{"CFSAUID":"R2L","PRUID":"46","PRNAME":"Manitoba"},{"CFSAUID":"R2M","PRUID":"46","PRNAME":"Manitoba"},{"CFSAUID":"S7M","PRUID":"47","PRNAME":"Saskatchewan"},{"CFSAUID":"T3E","PRUID":"48","PRNAME":"Alberta"},{"CFSAUID":"T3G","PRUID":"48","PRNAME":"Alberta"},{"CFSAUID":"N4W","PRUID":"35","PRNAME":"Ontario"},{"CFSAUID":"S0H","PRUID":"47","PRNAME":"Saskatchewan"},{"CFSAUID":"S0J","PRUID":"47","PRNAME":"Saskatchewan"},{"CFSAUID":"S0K","PRUID":"47","PRNAME":"Saskatchewan"},{"CFSAUID":"S0L","PRUID":"47","PRNAME":"Saskatchewan"},{"CFSAUID":"S0M","PRUID":"47","PRNAME":"Saskatchewan"},{"CFSAUID":"S0N","PRUID":"47","PRNAME":"Saskatchewan"},{"CFSAUID":"S0P","PRUID":"47","PRNAME":"Saskatchewan"},{"CFSAUID":"T3M","PRUID":"48","PRNAME":"Alberta"},{"CFSAUID":"T3N","PRUID":"48","PRNAME":"Alberta"},{"CFSAUID":"T1L","PRUID":"48","PRNAME":"Alberta"},{"CFSAUID":"L1P","PRUID":"35","PRNAME":"Ontario"},{"CFSAUID":"L1R","PRUID":"35","PRNAME":"Ontario"},{"CFSAUID":"L1S","PRUID":"35","PRNAME":"Ontario"},{"CFSAUID":"S7N","PRUID":"47","PRNAME":"Saskatchewan"},{"CFSAUID":"S7P","PRUID":"47","PRNAME":"Saskatchewan"},{"CFSAUID":"S7R","PRUID":"47","PRNAME":"Saskatchewan"},{"CFSAUID":"T5M","PRUID":"48","PRNAME":"Alberta"},{"CFSAUID":"N4X","PRUID":"35","PRNAME":"Ontario"},{"CFSAUID":"N4Z","PRUID":"35","PRNAME":"Ontario"},{"CFSAUID":"N5A","PRUID":"35","PRNAME":"Ontario"},{"CFSAUID":"N8A","PRUID":"35","PRNAME":"Ontario"},{"CFSAUID":"T3P","PRUID":"48","PRNAME":"Alberta"},{"CFSAUID":"N5W","PRUID":"35","PRNAME":"Ontario"},{"CFSAUID":"L1T","PRUID":"35","PRNAME":"Ontario"},{"CFSAUID":"N8W","PRUID":"35","PRNAME":"Ontario"},{"CFSAUID":"N8X","PRUID":"35","PRNAME":"Ontario"},{"CFSAUID":"T5N","PRUID":"48","PRNAME":"Alberta"},{"CFSAUID":"T5P","PRUID":"48","PRNAME":"Alberta"},{"CFSAUID":"T5R","PRUID":"48","PRNAME":"Alberta"},{"CFSAUID":"N7V","PRUID":"35","PRNAME":"Ontario"},{"CFSAUID":"P3P","PRUID":"35","PRNAME":"Ontario"},{"CFSAUID":"P3Y","PRUID":"35","PRNAME":"Ontario"},{"CFSAUID":"P4N","PRUID":"35","PRNAME":"Ontario"},{"CFSAUID":"P4P","PRUID":"35","PRNAME":"Ontario"},{"CFSAUID":"N5X","PRUID":"35","PRNAME":"Ontario"},{"CFSAUID":"P6B","PRUID":"35","PRNAME":"Ontario"},{"CFSAUID":"P6C","PRUID":"35","PRNAME":"Ontario"},{"CFSAUID":"P7A","PRUID":"35","PRNAME":"Ontario"},{"CFSAUID":"P7C","PRUID":"35","PRNAME":"Ontario"},{"CFSAUID":"P7G","PRUID":"35","PRNAME":"Ontario"},{"CFSAUID":"P7J","PRUID":"35","PRNAME":"Ontario"},{"CFSAUID":"N8Y","PRUID":"35","PRNAME":"Ontario"},{"CFSAUID":"R3C","PRUID":"46","PRNAME":"Manitoba"},{"CFSAUID":"R3E","PRUID":"46","PRNAME":"Manitoba"},{"CFSAUID":"R3G","PRUID":"46","PRNAME":"Manitoba"},{"CFSAUID":"R3H","PRUID":"46","PRNAME":"Manitoba"},{"CFSAUID":"N7W","PRUID":"35","PRNAME":"Ontario"},{"CFSAUID":"N7X","PRUID":"35","PRNAME":"Ontario"},{"CFSAUID":"R2N","PRUID":"46","PRNAME":"Manitoba"},{"CFSAUID":"R2P","PRUID":"46","PRNAME":"Manitoba"},{"CFSAUID":"R7B","PRUID":"46","PRNAME":"Manitoba"},{"CFSAUID":"R7C","PRUID":"46","PRNAME":"Manitoba"},{"CFSAUID":"R7N","PRUID":"46","PRNAME":"Manitoba"},{"CFSAUID":"P7B","PRUID":"35","PRNAME":"Ontario"},{"CFSAUID":"P7K","PRUID":"35","PRNAME":"Ontario"},{"CFSAUID":"P7L","PRUID":"35","PRNAME":"Ontario"},{"CFSAUID":"S2V","PRUID":"47","PRNAME":"Saskatchewan"},{"CFSAUID":"S3N","PRUID":"47","PRNAME":"Saskatchewan"},{"CFSAUID":"S4A","PRUID":"47","PRNAME":"Saskatchewan"},{"CFSAUID":"T1M","PRUID":"48","PRNAME":"Alberta"},{"CFSAUID":"T1P","PRUID":"48","PRNAME":"Alberta"},{"CFSAUID":"T1R","PRUID":"48","PRNAME":"Alberta"},{"CFSAUID":"T1S","PRUID":"48","PRNAME":"Alberta"},{"CFSAUID":"T1V","PRUID":"48","PRNAME":"Alberta"},{"CFSAUID":"T1W","PRUID":"48","PRNAME":"Alberta"},{"CFSAUID":"T1X","PRUID":"48","PRNAME":"Alberta"},{"CFSAUID":"T1Y","PRUID":"48","PRNAME":"Alberta"},{"CFSAUID":"T1Z","PRUID":"48","PRNAME":"Alberta"},{"CFSAUID":"T2A","PRUID":"48","PRNAME":"Alberta"},{"CFSAUID":"R2R","PRUID":"46","PRNAME":"Manitoba"},{"CFSAUID":"R2V","PRUID":"46","PRNAME":"Manitoba"},{"CFSAUID":"S7S","PRUID":"47","PRNAME":"Saskatchewan"},{"CFSAUID":"S7T","PRUID":"47","PRNAME":"Saskatchewan"},{"CFSAUID":"S7V","PRUID":"47","PRNAME":"Saskatchewan"},{"CFSAUID":"T3H","PRUID":"48","PRNAME":"Alberta"},{"CFSAUID":"T3J","PRUID":"48","PRNAME":"Alberta"},{"CFSAUID":"N5R","PRUID":"35","PRNAME":"Ontario"},{"CFSAUID":"T3R","PRUID":"48","PRNAME":"Alberta"},{"CFSAUID":"T3S","PRUID":"48","PRNAME":"Alberta"},{"CFSAUID":"T4A","PRUID":"48","PRNAME":"Alberta"},{"CFSAUID":"L1V","PRUID":"35","PRNAME":"Ontario"},{"CFSAUID":"L1W","PRUID":"35","PRNAME":"Ontario"},{"CFSAUID":"L1X","PRUID":"35","PRNAME":"Ontario"},{"CFSAUID":"S7W","PRUID":"47","PRNAME":"Saskatchewan"},{"CFSAUID":"S9A","PRUID":"47","PRNAME":"Saskatchewan"},{"CFSAUID":"S9H","PRUID":"47","PRNAME":"Saskatchewan"},{"CFSAUID":"S9V","PRUID":"47","PRNAME":"Saskatchewan"},{"CFSAUID":"S9X","PRUID":"47","PRNAME":"Saskatchewan"},{"CFSAUID":"T0A","PRUID":"48","PRNAME":"Alberta"},{"CFSAUID":"T0B","PRUID":"48","PRNAME":"Alberta"},{"CFSAUID":"T0C","PRUID":"48","PRNAME":"Alberta"},{"CFSAUID":"T0E","PRUID":"48","PRNAME":"Alberta"},{"CFSAUID":"T0G","PRUID":"48","PRNAME":"Alberta"},{"CFSAUID":"T0H","PRUID":"48","PRNAME":"Alberta"},{"CFSAUID":"T0J","PRUID":"48","PRNAME":"Alberta"},{"CFSAUID":"T0K","PRUID":"48","PRNAME":"Alberta"},{"CFSAUID":"T0L","PRUID":"48","PRNAME":"Alberta"},{"CFSAUID":"T0M","PRUID":"48","PRNAME":"Alberta"},{"CFSAUID":"T5S","PRUID":"48","PRNAME":"Alberta"},{"CFSAUID":"V3C","PRUID":"59","PRNAME":"British Columbia / Colombie-Britannique"},{"CFSAUID":"V5Z","PRUID":"59","PRNAME":"British Columbia / Colombie-Britannique"},{"CFSAUID":"V6A","PRUID":"59","PRNAME":"British Columbia / Colombie-Britannique"},{"CFSAUID":"V8N","PRUID":"59","PRNAME":"British Columbia / Colombie-Britannique"},{"CFSAUID":"V1Y","PRUID":"59","PRNAME":"British Columbia / Colombie-Britannique"},{"CFSAUID":"T6W","PRUID":"48","PRNAME":"Alberta"},{"CFSAUID":"T6X","PRUID":"48","PRNAME":"Alberta"},{"CFSAUID":"T7A","PRUID":"48","PRNAME":"Alberta"},{"CFSAUID":"T7E","PRUID":"48","PRNAME":"Alberta"},{"CFSAUID":"T7N","PRUID":"48","PRNAME":"Alberta"},{"CFSAUID":"V3N","PRUID":"59","PRNAME":"British Columbia / Colombie-Britannique"},{"CFSAUID":"V7B","PRUID":"59","PRNAME":"British Columbia / Colombie-Britannique"},{"CFSAUID":"V7C","PRUID":"59","PRNAME":"British Columbia / Colombie-Britannique"},{"CFSAUID":"T8X","PRUID":"48","PRNAME":"Alberta"},{"CFSAUID":"V3R","PRUID":"59","PRNAME":"British Columbia / Colombie-Britannique"},{"CFSAUID":"V6S","PRUID":"59","PRNAME":"British Columbia / Colombie-Britannique"},{"CFSAUID":"V6T","PRUID":"59","PRNAME":"British Columbia / Colombie-Britannique"},{"CFSAUID":"T9E","PRUID":"48","PRNAME":"Alberta"},{"CFSAUID":"V4A","PRUID":"59","PRNAME":"British Columbia / Colombie-Britannique"},{"CFSAUID":"V4B","PRUID":"59","PRNAME":"British Columbia / Colombie-Britannique"},{"CFSAUID":"V6V","PRUID":"59","PRNAME":"British Columbia / Colombie-Britannique"},{"CFSAUID":"T7P","PRUID":"48","PRNAME":"Alberta"},{"CFSAUID":"T7S","PRUID":"48","PRNAME":"Alberta"},{"CFSAUID":"T7V","PRUID":"48","PRNAME":"Alberta"},{"CFSAUID":"T7X","PRUID":"48","PRNAME":"Alberta"},{"CFSAUID":"T7Y","PRUID":"48","PRNAME":"Alberta"},{"CFSAUID":"T7Z","PRUID":"48","PRNAME":"Alberta"},{"CFSAUID":"T8A","PRUID":"48","PRNAME":"Alberta"},{"CFSAUID":"T8B","PRUID":"48","PRNAME":"Alberta"},{"CFSAUID":"T8E","PRUID":"48","PRNAME":"Alberta"},{"CFSAUID":"T8G","PRUID":"48","PRNAME":"Alberta"},{"CFSAUID":"T8L","PRUID":"48","PRNAME":"Alberta"},{"CFSAUID":"T8N","PRUID":"48","PRNAME":"Alberta"},{"CFSAUID":"T8R","PRUID":"48","PRNAME":"Alberta"},{"CFSAUID":"T8S","PRUID":"48","PRNAME":"Alberta"},{"CFSAUID":"V4C","PRUID":"59","PRNAME":"British Columbia / Colombie-Britannique"},{"CFSAUID":"V4E","PRUID":"59","PRNAME":"British Columbia / Colombie-Britannique"},{"CFSAUID":"V7E","PRUID":"59","PRNAME":"British Columbia / Colombie-Britannique"},{"CFSAUID":"T8C","PRUID":"48","PRNAME":"Alberta"},{"CFSAUID":"V3S","PRUID":"59","PRNAME":"British Columbia / Colombie-Britannique"},{"CFSAUID":"V3T","PRUID":"59","PRNAME":"British Columbia / Colombie-Britannique"},{"CFSAUID":"V7G","PRUID":"59","PRNAME":"British Columbia / Colombie-Britannique"},{"CFSAUID":"V7H","PRUID":"59","PRNAME":"British Columbia / Colombie-Britannique"},{"CFSAUID":"V7J","PRUID":"59","PRNAME":"British Columbia / Colombie-Britannique"},{"CFSAUID":"V7W","PRUID":"59","PRNAME":"British Columbia / Colombie-Britannique"},{"CFSAUID":"V8A","PRUID":"59","PRNAME":"British Columbia / Colombie-Britannique"},{"CFSAUID":"V8B","PRUID":"59","PRNAME":"British Columbia / Colombie-Britannique"},{"CFSAUID":"V8C","PRUID":"59","PRNAME":"British Columbia / Colombie-Britannique"},{"CFSAUID":"V8G","PRUID":"59","PRNAME":"British Columbia / Colombie-Britannique"},{"CFSAUID":"V8J","PRUID":"59","PRNAME":"British Columbia / Colombie-Britannique"},{"CFSAUID":"V8K","PRUID":"59","PRNAME":"British Columbia / Colombie-Britannique"},{"CFSAUID":"V8L","PRUID":"59","PRNAME":"British Columbia / Colombie-Britannique"},{"CFSAUID":"V3V","PRUID":"59","PRNAME":"British Columbia / Colombie-Britannique"},{"CFSAUID":"V6W","PRUID":"59","PRNAME":"British Columbia / Colombie-Britannique"},{"CFSAUID":"V6X","PRUID":"59","PRNAME":"British Columbia / Colombie-Britannique"},{"CFSAUID":"V6Y","PRUID":"59","PRNAME":"British Columbia / Colombie-Britannique"},{"CFSAUID":"T9G","PRUID":"48","PRNAME":"Alberta"},{"CFSAUID":"T9H","PRUID":"48","PRNAME":"Alberta"},{"CFSAUID":"T9J","PRUID":"48","PRNAME":"Alberta"},{"CFSAUID":"T9K","PRUID":"48","PRNAME":"Alberta"},{"CFSAUID":"T9M","PRUID":"48","PRNAME":"Alberta"},{"CFSAUID":"T9N","PRUID":"48","PRNAME":"Alberta"},{"CFSAUID":"T9S","PRUID":"48","PRNAME":"Alberta"},{"CFSAUID":"T9V","PRUID":"48","PRNAME":"Alberta"},{"CFSAUID":"T9W","PRUID":"48","PRNAME":"Alberta"},{"CFSAUID":"V0A","PRUID":"59","PRNAME":"British Columbia / Colombie-Britannique"},{"CFSAUID":"V0B","PRUID":"59","PRNAME":"British Columbia / Colombie-Britannique"},{"CFSAUID":"V0C","PRUID":"59","PRNAME":"British Columbia / Colombie-Britannique"},{"CFSAUID":"V0E","PRUID":"59","PRNAME":"British Columbia / Colombie-Britannique"},{"CFSAUID":"V0G","PRUID":"59","PRNAME":"British Columbia / Colombie-Britannique"},{"CFSAUID":"V0H","PRUID":"59","PRNAME":"British Columbia / Colombie-Britannique"},{"CFSAUID":"V0J","PRUID":"59","PRNAME":"British Columbia / Colombie-Britannique"},{"CFSAUID":"V0K","PRUID":"59","PRNAME":"British Columbia / Colombie-Britannique"},{"CFSAUID":"V6Z","PRUID":"59","PRNAME":"British Columbia / Colombie-Britannique"},{"CFSAUID":"T8H","PRUID":"48","PRNAME":"Alberta"},{"CFSAUID":"T8T","PRUID":"48","PRNAME":"Alberta"},{"CFSAUID":"T8V","PRUID":"48","PRNAME":"Alberta"},{"CFSAUID":"T8W","PRUID":"48","PRNAME":"Alberta"},{"CFSAUID":"V4G","PRUID":"59","PRNAME":"British Columbia / Colombie-Britannique"},{"CFSAUID":"V4L","PRUID":"59","PRNAME":"British Columbia / Colombie-Britannique"},{"CFSAUID":"V4M","PRUID":"59","PRNAME":"British Columbia / Colombie-Britannique"},{"CFSAUID":"T9A","PRUID":"48","PRNAME":"Alberta"},{"CFSAUID":"T9C","PRUID":"48","PRNAME":"Alberta"},{"CFSAUID":"V3W","PRUID":"59","PRNAME":"British Columbia / Colombie-Britannique"},{"CFSAUID":"V3X","PRUID":"59","PRNAME":"British Columbia / Colombie-Britannique"},{"CFSAUID":"V7K","PRUID":"59","PRNAME":"British Columbia / Colombie-Britannique"},{"CFSAUID":"V7L","PRUID":"59","PRNAME":"British Columbia / Colombie-Britannique"},{"CFSAUID":"V7M","PRUID":"59","PRNAME":"British Columbia / Colombie-Britannique"},{"CFSAUID":"V3Y","PRUID":"59","PRNAME":"British Columbia / Colombie-Britannique"},{"CFSAUID":"V3Z","PRUID":"59","PRNAME":"British Columbia / Colombie-Britannique"},{"CFSAUID":"V4K","PRUID":"59","PRNAME":"British Columbia / Colombie-Britannique"},{"CFSAUID":"V7A","PRUID":"59","PRNAME":"British Columbia / Colombie-Britannique"},{"CFSAUID":"T9X","PRUID":"48","PRNAME":"Alberta"},{"CFSAUID":"V0L","PRUID":"59","PRNAME":"British Columbia / Colombie-Britannique"},{"CFSAUID":"V0M","PRUID":"59","PRNAME":"British Columbia / Colombie-Britannique"},{"CFSAUID":"V0N","PRUID":"59","PRNAME":"British Columbia / Colombie-Britannique"},{"CFSAUID":"V0P","PRUID":"59","PRNAME":"British Columbia / Colombie-Britannique"},{"CFSAUID":"V0R","PRUID":"59","PRNAME":"British Columbia / Colombie-Britannique"},{"CFSAUID":"V0S","PRUID":"59","PRNAME":"British Columbia / Colombie-Britannique"},{"CFSAUID":"V0T","PRUID":"59","PRNAME":"British Columbia / Colombie-Britannique"},{"CFSAUID":"V0V","PRUID":"59","PRNAME":"British Columbia / Colombie-Britannique"},{"CFSAUID":"V0W","PRUID":"59","PRNAME":"British Columbia / Colombie-Britannique"},{"CFSAUID":"V0X","PRUID":"59","PRNAME":"British Columbia / Colombie-Britannique"},{"CFSAUID":"V1B","PRUID":"59","PRNAME":"British Columbia / Colombie-Britannique"},{"CFSAUID":"V1C","PRUID":"59","PRNAME":"British Columbia / Colombie-Britannique"},{"CFSAUID":"V1E","PRUID":"59","PRNAME":"British Columbia / Colombie-Britannique"},{"CFSAUID":"V1G","PRUID":"59","PRNAME":"British Columbia / Colombie-Britannique"},{"CFSAUID":"V1H","PRUID":"59","PRNAME":"British Columbia / Colombie-Britannique"},{"CFSAUID":"V1J","PRUID":"59","PRNAME":"British Columbia / Colombie-Britannique"},{"CFSAUID":"V5J","PRUID":"59","PRNAME":"British Columbia / Colombie-Britannique"},{"CFSAUID":"V5K","PRUID":"59","PRNAME":"British Columbia / Colombie-Britannique"},{"CFSAUID":"V5L","PRUID":"59","PRNAME":"British Columbia / Colombie-Britannique"},{"CFSAUID":"V5M","PRUID":"59","PRNAME":"British Columbia / Colombie-Britannique"},{"CFSAUID":"V8W","PRUID":"59","PRNAME":"British Columbia / Colombie-Britannique"},{"CFSAUID":"V4N","PRUID":"59","PRNAME":"British Columbia / Colombie-Britannique"},{"CFSAUID":"V4P","PRUID":"59","PRNAME":"British Columbia / Colombie-Britannique"},{"CFSAUID":"V4R","PRUID":"59","PRNAME":"British Columbia / Colombie-Britannique"},{"CFSAUID":"V7N","PRUID":"59","PRNAME":"British Columbia / Colombie-Britannique"},{"CFSAUID":"V6B","PRUID":"59","PRNAME":"British Columbia / Colombie-Britannique"},{"CFSAUID":"V6C","PRUID":"59","PRNAME":"British Columbia / Colombie-Britannique"},{"CFSAUID":"V6E","PRUID":"59","PRNAME":"British Columbia / Colombie-Britannique"},{"CFSAUID":"T6H","PRUID":"48","PRNAME":"Alberta"},{"CFSAUID":"T6J","PRUID":"48","PRNAME":"Alberta"},{"CFSAUID":"T6K","PRUID":"48","PRNAME":"Alberta"},{"CFSAUID":"V8X","PRUID":"59","PRNAME":"British Columbia / Colombie-Britannique"},{"CFSAUID":"V8Y","PRUID":"59","PRNAME":"British Columbia / Colombie-Britannique"},{"CFSAUID":"V8Z","PRUID":"59","PRNAME":"British Columbia / Colombie-Britannique"},{"CFSAUID":"V9A","PRUID":"59","PRNAME":"British Columbia / Colombie-Britannique"},{"CFSAUID":"V9B","PRUID":"59","PRNAME":"British Columbia / Colombie-Britannique"},{"CFSAUID":"V9C","PRUID":"59","PRNAME":"British Columbia / Colombie-Britannique"},{"CFSAUID":"V9E","PRUID":"59","PRNAME":"British Columbia / Colombie-Britannique"},{"CFSAUID":"V9G","PRUID":"59","PRNAME":"British Columbia / Colombie-Britannique"},{"CFSAUID":"V9H","PRUID":"59","PRNAME":"British Columbia / Colombie-Britannique"},{"CFSAUID":"V9J","PRUID":"59","PRNAME":"British Columbia / Colombie-Britannique"},{"CFSAUID":"V9K","PRUID":"59","PRNAME":"British Columbia / Colombie-Britannique"},{"CFSAUID":"V9L","PRUID":"59","PRNAME":"British Columbia / Colombie-Britannique"},{"CFSAUID":"V9N","PRUID":"59","PRNAME":"British Columbia / Colombie-Britannique"},{"CFSAUID":"V9P","PRUID":"59","PRNAME":"British Columbia / Colombie-Britannique"},{"CFSAUID":"V9R","PRUID":"59","PRNAME":"British Columbia / Colombie-Britannique"},{"CFSAUID":"V9S","PRUID":"59","PRNAME":"British Columbia / Colombie-Britannique"},{"CFSAUID":"V9T","PRUID":"59","PRNAME":"British Columbia / Colombie-Britannique"},{"CFSAUID":"V5R","PRUID":"59","PRNAME":"British Columbia / Colombie-Britannique"},{"CFSAUID":"V7P","PRUID":"59","PRNAME":"British Columbia / Colombie-Britannique"},{"CFSAUID":"V7R","PRUID":"59","PRNAME":"British Columbia / Colombie-Britannique"},{"CFSAUID":"V1A","PRUID":"59","PRNAME":"British Columbia / Colombie-Britannique"},{"CFSAUID":"V1K","PRUID":"59","PRNAME":"British Columbia / Colombie-Britannique"},{"CFSAUID":"V1L","PRUID":"59","PRNAME":"British Columbia / Colombie-Britannique"},{"CFSAUID":"V1N","PRUID":"59","PRNAME":"British Columbia / Colombie-Britannique"},{"CFSAUID":"V1P","PRUID":"59","PRNAME":"British Columbia / Colombie-Britannique"},{"CFSAUID":"V1R","PRUID":"59","PRNAME":"British Columbia / Colombie-Britannique"},{"CFSAUID":"V1S","PRUID":"59","PRNAME":"British Columbia / Colombie-Britannique"},{"CFSAUID":"V4T","PRUID":"59","PRNAME":"British Columbia / Colombie-Britannique"},{"CFSAUID":"V2L","PRUID":"59","PRNAME":"British Columbia / Colombie-Britannique"},{"CFSAUID":"V2R","PRUID":"59","PRNAME":"British Columbia / Colombie-Britannique"},{"CFSAUID":"V5A","PRUID":"59","PRNAME":"British Columbia / Colombie-Britannique"},{"CFSAUID":"T6L","PRUID":"48","PRNAME":"Alberta"},{"CFSAUID":"V3E","PRUID":"59","PRNAME":"British Columbia / Colombie-Britannique"},{"CFSAUID":"Y1A","PRUID":"60","PRNAME":"Yukon"},{"CFSAUID":"V5N","PRUID":"59","PRNAME":"British Columbia / Colombie-Britannique"},{"CFSAUID":"V5P","PRUID":"59","PRNAME":"British Columbia / Colombie-Britannique"},{"CFSAUID":"V1M","PRUID":"59","PRNAME":"British Columbia / Colombie-Britannique"},{"CFSAUID":"V4S","PRUID":"59","PRNAME":"British Columbia / Colombie-Britannique"},{"CFSAUID":"V1T","PRUID":"59","PRNAME":"British Columbia / Colombie-Britannique"},{"CFSAUID":"V1X","PRUID":"59","PRNAME":"British Columbia / Colombie-Britannique"},{"CFSAUID":"V1Z","PRUID":"59","PRNAME":"British Columbia / Colombie-Britannique"},{"CFSAUID":"V2A","PRUID":"59","PRNAME":"British Columbia / Colombie-Britannique"},{"CFSAUID":"V2B","PRUID":"59","PRNAME":"British Columbia / Colombie-Britannique"},{"CFSAUID":"V2C","PRUID":"59","PRNAME":"British Columbia / Colombie-Britannique"},{"CFSAUID":"V5B","PRUID":"59","PRNAME":"British Columbia / Colombie-Britannique"},{"CFSAUID":"V5C","PRUID":"59","PRNAME":"British Columbia / Colombie-Britannique"},{"CFSAUID":"V8P","PRUID":"59","PRNAME":"British Columbia / Colombie-Britannique"},{"CFSAUID":"V3G","PRUID":"59","PRNAME":"British Columbia / Colombie-Britannique"},{"CFSAUID":"V3H","PRUID":"59","PRNAME":"British Columbia / Colombie-Britannique"},{"CFSAUID":"V6G","PRUID":"59","PRNAME":"British Columbia / Colombie-Britannique"},{"CFSAUID":"V5S","PRUID":"59","PRNAME":"British Columbia / Colombie-Britannique"},{"CFSAUID":"V5T","PRUID":"59","PRNAME":"British Columbia / Colombie-Britannique"},{"CFSAUID":"T5X","PRUID":"48","PRNAME":"Alberta"},{"CFSAUID":"T5Y","PRUID":"48","PRNAME":"Alberta"},{"CFSAUID":"V4V","PRUID":"59","PRNAME":"British Columbia / Colombie-Britannique"},{"CFSAUID":"V7S","PRUID":"59","PRNAME":"British Columbia / Colombie-Britannique"},{"CFSAUID":"V7T","PRUID":"59","PRNAME":"British Columbia / Colombie-Britannique"},{"CFSAUID":"V8R","PRUID":"59","PRNAME":"British Columbia / Colombie-Britannique"},{"CFSAUID":"V2S","PRUID":"59","PRNAME":"British Columbia / Colombie-Britannique"},{"CFSAUID":"V6H","PRUID":"59","PRNAME":"British Columbia / Colombie-Britannique"},{"CFSAUID":"V6J","PRUID":"59","PRNAME":"British Columbia / Colombie-Britannique"},{"CFSAUID":"V6K","PRUID":"59","PRNAME":"British Columbia / Colombie-Britannique"},{"CFSAUID":"T5Z","PRUID":"48","PRNAME":"Alberta"},{"CFSAUID":"T6A","PRUID":"48","PRNAME":"Alberta"},{"CFSAUID":"V2Z","PRUID":"59","PRNAME":"British Columbia / Colombie-Britannique"},{"CFSAUID":"V7V","PRUID":"59","PRNAME":"British Columbia / Colombie-Britannique"},{"CFSAUID":"V1V","PRUID":"59","PRNAME":"British Columbia / Colombie-Britannique"},{"CFSAUID":"V2T","PRUID":"59","PRNAME":"British Columbia / Colombie-Britannique"},{"CFSAUID":"V2V","PRUID":"59","PRNAME":"British Columbia / Colombie-Britannique"},{"CFSAUID":"V2W","PRUID":"59","PRNAME":"British Columbia / Colombie-Britannique"},{"CFSAUID":"V9V","PRUID":"59","PRNAME":"British Columbia / Colombie-Britannique"},{"CFSAUID":"V9W","PRUID":"59","PRNAME":"British Columbia / Colombie-Britannique"},{"CFSAUID":"V9X","PRUID":"59","PRNAME":"British Columbia / Colombie-Britannique"},{"CFSAUID":"T6M","PRUID":"48","PRNAME":"Alberta"},{"CFSAUID":"T6P","PRUID":"48","PRNAME":"Alberta"},{"CFSAUID":"T6R","PRUID":"48","PRNAME":"Alberta"},{"CFSAUID":"T6S","PRUID":"48","PRNAME":"Alberta"},{"CFSAUID":"T6T","PRUID":"48","PRNAME":"Alberta"},{"CFSAUID":"V3A","PRUID":"59","PRNAME":"British Columbia / Colombie-Britannique"},{"CFSAUID":"V5V","PRUID":"59","PRNAME":"British Columbia / Colombie-Britannique"},{"CFSAUID":"V5W","PRUID":"59","PRNAME":"British Columbia / Colombie-Britannique"},{"CFSAUID":"V5X","PRUID":"59","PRNAME":"British Columbia / Colombie-Britannique"},{"CFSAUID":"V1W","PRUID":"59","PRNAME":"British Columbia / Colombie-Britannique"},{"CFSAUID":"V2E","PRUID":"59","PRNAME":"British Columbia / Colombie-Britannique"},{"CFSAUID":"V2G","PRUID":"59","PRNAME":"British Columbia / Colombie-Britannique"},{"CFSAUID":"V2H","PRUID":"59","PRNAME":"British Columbia / Colombie-Britannique"},{"CFSAUID":"V2J","PRUID":"59","PRNAME":"British Columbia / Colombie-Britannique"},{"CFSAUID":"V2K","PRUID":"59","PRNAME":"British Columbia / Colombie-Britannique"},{"CFSAUID":"V2M","PRUID":"59","PRNAME":"British Columbia / Colombie-Britannique"},{"CFSAUID":"V2N","PRUID":"59","PRNAME":"British Columbia / Colombie-Britannique"},{"CFSAUID":"V2P","PRUID":"59","PRNAME":"British Columbia / Colombie-Britannique"},{"CFSAUID":"V4W","PRUID":"59","PRNAME":"British Columbia / Colombie-Britannique"},{"CFSAUID":"V3J","PRUID":"59","PRNAME":"British Columbia / Colombie-Britannique"},{"CFSAUID":"V3K","PRUID":"59","PRNAME":"British Columbia / Colombie-Britannique"},{"CFSAUID":"V3L","PRUID":"59","PRNAME":"British Columbia / Colombie-Britannique"},{"CFSAUID":"V3M","PRUID":"59","PRNAME":"British Columbia / Colombie-Britannique"},{"CFSAUID":"V5Y","PRUID":"59","PRNAME":"British Columbia / Colombie-Britannique"},{"CFSAUID":"T6B","PRUID":"48","PRNAME":"Alberta"},{"CFSAUID":"T6C","PRUID":"48","PRNAME":"Alberta"},{"CFSAUID":"V4X","PRUID":"59","PRNAME":"British Columbia / Colombie-Britannique"},{"CFSAUID":"V4Z","PRUID":"59","PRNAME":"British Columbia / Colombie-Britannique"},{"CFSAUID":"V8M","PRUID":"59","PRNAME":"British Columbia / Colombie-Britannique"},{"CFSAUID":"V6L","PRUID":"59","PRNAME":"British Columbia / Colombie-Britannique"},{"CFSAUID":"V6M","PRUID":"59","PRNAME":"British Columbia / Colombie-Britannique"},{"CFSAUID":"V6N","PRUID":"59","PRNAME":"British Columbia / Colombie-Britannique"},{"CFSAUID":"V6P","PRUID":"59","PRNAME":"British Columbia / Colombie-Britannique"},{"CFSAUID":"V6R","PRUID":"59","PRNAME":"British Columbia / Colombie-Britannique"},{"CFSAUID":"T6V","PRUID":"48","PRNAME":"Alberta"},{"CFSAUID":"T6E","PRUID":"48","PRNAME":"Alberta"},{"CFSAUID":"T6G","PRUID":"48","PRNAME":"Alberta"},{"CFSAUID":"V3B","PRUID":"59","PRNAME":"British Columbia / Colombie-Britannique"}]